{
  "areas": [],
  "bounds": {
    "max_x": -540,
    "max_z": 720,
    "min_x": -720,
    "min_z": 540
  },
  "buildings": [
    {
      "building": "yes",
      "footprint": [
        {
          "x": -543.955,
          "z": 691.553
        },
        {
          "x": -543.918,
          "z": 688.047
        },
        {
          "x": -545.154,
          "z": 688.036
        },
        {
          "x": -545.127,
          "z": 686.076
        },
        {
          "x": -547.13,
          "z": 686.054
        },
        {
          "x": -547.047,
          "z": 679.33
        },
        {
          "x": -534.835,
          "z": 679.486
        },
        {
          "x": -534.928,
          "z": 686.989
        },
        {
          "x": -531.623,
          "z": 687.023
        },
        {
          "x": -531.679,
          "z": 691.709
        },
        {
          "x": -543.955,
          "z": 691.553
        }
      ],
      "height_m": 0,
      "id": "way/411123482",
      "levels": 0,
      "name": null
    },
    {
      "building": "house",
      "footprint": [
        {
          "x": -643.168,
          "z": 695.071
        },
        {
          "x": -643.214,
          "z": 698.221
        },
        {
          "x": -641.368,
          "z": 698.255
        },
        {
          "x": -641.396,
          "z": 700.158
        },
        {
          "x": -643.584,
          "z": 700.125
        },
        {
          "x": -643.676,
          "z": 705.958
        },
        {
          "x": -628.437,
          "z": 706.181
        },
        {
          "x": -628.373,
          "z": 701.349
        },
        {
          "x": -631.594,
          "z": 701.294
        },
        {
          "x": -631.502,
          "z": 695.238
        },
        {
          "x": -643.168,
          "z": 695.071
        }
      ],
      "height_m": 6.8,
      "id": "way/411123485",
      "levels": 0,
      "name": null
    },
    {
      "building": "house",
      "footprint": [
        {
          "x": -599.381,
          "z": 716.667
        },
        {
          "x": -600.175,
          "z": 716.667
        },
        {
          "x": -600.193,
          "z": 721.999
        },
        {
          "x": -583.395,
          "z": 722.044
        },
        {
          "x": -583.376,
          "z": 712.493
        },
        {
          "x": -584.631,
          "z": 712.481
        },
        {
          "x": -584.631,
          "z": 710.656
        },
        {
          "x": -593.317,
          "z": 710.633
        },
        {
          "x": -593.317,
          "z": 712.225
        },
        {
          "x": -599.363,
          "z": 712.214
        },
        {
          "x": -599.381,
          "z": 716.667
        }
      ],
      "height_m": 5.3,
      "id": "way/411123497",
      "levels": 0,
      "name": null
    },
    {
      "building": "house",
      "footprint": [
        {
          "x": -535.02,
          "z": 570.704
        },
        {
          "x": -541.933,
          "z": 570.671
        },
        {
          "x": -541.933,
          "z": 570.359
        },
        {
          "x": -545.819,
          "z": 570.337
        },
        {
          "x": -545.828,
          "z": 573.654
        },
        {
          "x": -544.462,
          "z": 573.654
        },
        {
          "x": -544.471,
          "z": 576.793
        },
        {
          "x": -546.742,
          "z": 576.782
        },
        {
          "x": -546.77,
          "z": 581.636
        },
        {
          "x": -535.075,
          "z": 581.692
        },
        {
          "x": -535.02,
          "z": 570.704
        }
      ],
      "height_m": 5.1,
      "id": "way/411123506",
      "levels": 0,
      "name": null
    },
    {
      "building": "house",
      "footprint": [
        {
          "x": -679.959,
          "z": 667.708
        },
        {
          "x": -679.913,
          "z": 662.989
        },
        {
          "x": -682.415,
          "z": 662.977
        },
        {
          "x": -682.378,
          "z": 659.181
        },
        {
          "x": -680.836,
          "z": 659.204
        },
        {
          "x": -680.818,
          "z": 656.933
        },
        {
          "x": -692.835,
          "z": 656.833
        },
        {
          "x": -692.9,
          "z": 664.024
        },
        {
          "x": -700.053,
          "z": 663.968
        },
        {
          "x": -700.09,
          "z": 667.53
        },
        {
          "x": -679.959,
          "z": 667.708
        }
      ],
      "height_m": 3.9,
      "id": "way/411123507",
      "levels": 0,
      "name": null
    },
    {
      "building": "house",
      "footprint": [
        {
          "x": -702.453,
          "z": 592.156
        },
        {
          "x": -702.434,
          "z": 590.085
        },
        {
          "x": -701.567,
          "z": 590.096
        },
        {
          "x": -701.548,
          "z": 588.582
        },
        {
          "x": -702.416,
          "z": 588.571
        },
        {
          "x": -702.398,
          "z": 586.501
        },
        {
          "x": -707.88,
          "z": 586.445
        },
        {
          "x": -707.899,
          "z": 588.671
        },
        {
          "x": -708.416,
          "z": 588.671
        },
        {
          "x": -708.434,
          "z": 590.909
        },
        {
          "x": -707.926,
          "z": 590.92
        },
        {
          "x": -707.936,
          "z": 592.089
        },
        {
          "x": -702.453,
          "z": 592.156
        }
      ],
      "height_m": 5.2,
      "id": "way/411123520",
      "levels": 0,
      "name": null
    },
    {
      "building": "house",
      "footprint": [
        {
          "x": -589.154,
          "z": 548.24
        },
        {
          "x": -589.154,
          "z": 547.55
        },
        {
          "x": -582.896,
          "z": 547.605
        },
        {
          "x": -582.85,
          "z": 542.963
        },
        {
          "x": -583.754,
          "z": 542.963
        },
        {
          "x": -583.736,
          "z": 541.405
        },
        {
          "x": -585.139,
          "z": 541.394
        },
        {
          "x": -585.102,
          "z": 537.108
        },
        {
          "x": -592.338,
          "z": 537.041
        },
        {
          "x": -592.357,
          "z": 539.613
        },
        {
          "x": -599.483,
          "z": 539.557
        },
        {
          "x": -599.556,
          "z": 548.151
        },
        {
          "x": -589.154,
          "z": 548.24
        }
      ],
      "height_m": 4.5,
      "id": "way/411123521",
      "levels": 0,
      "name": null
    },
    {
      "building": "house",
      "footprint": [
        {
          "x": -629.905,
          "z": 547.95
        },
        {
          "x": -629.859,
          "z": 536.863
        },
        {
          "x": -635.083,
          "z": 536.841
        },
        {
          "x": -635.083,
          "z": 536.128
        },
        {
          "x": -636.19,
          "z": 536.128
        },
        {
          "x": -636.19,
          "z": 536.841
        },
        {
          "x": -641.599,
          "z": 536.807
        },
        {
          "x": -641.608,
          "z": 539.891
        },
        {
          "x": -640.722,
          "z": 539.891
        },
        {
          "x": -640.741,
          "z": 543.531
        },
        {
          "x": -642.762,
          "z": 543.52
        },
        {
          "x": -642.781,
          "z": 547.895
        },
        {
          "x": -629.905,
          "z": 547.95
        }
      ],
      "height_m": 4.3,
      "id": "way/411123542",
      "levels": 0,
      "name": null
    },
    {
      "building": "house",
      "footprint": [
        {
          "x": -681.307,
          "z": 637.285
        },
        {
          "x": -681.261,
          "z": 632.453
        },
        {
          "x": -682.654,
          "z": 632.431
        },
        {
          "x": -682.627,
          "z": 629.704
        },
        {
          "x": -680.67,
          "z": 629.726
        },
        {
          "x": -680.633,
          "z": 626.231
        },
        {
          "x": -693.98,
          "z": 626.097
        },
        {
          "x": -693.998,
          "z": 627.477
        },
        {
          "x": -694.718,
          "z": 627.477
        },
        {
          "x": -694.755,
          "z": 630.862
        },
        {
          "x": -693.915,
          "z": 630.873
        },
        {
          "x": -693.971,
          "z": 637.151
        },
        {
          "x": -681.307,
          "z": 637.285
        }
      ],
      "height_m": 5.0,
      "id": "way/411123557",
      "levels": 0,
      "name": null
    },
    {
      "building": "house",
      "footprint": [
        {
          "x": -677.532,
          "z": 707.127
        },
        {
          "x": -675.418,
          "z": 707.138
        },
        {
          "x": -675.381,
          "z": 702.095
        },
        {
          "x": -687.306,
          "z": 701.995
        },
        {
          "x": -687.353,
          "z": 707.427
        },
        {
          "x": -688.654,
          "z": 707.416
        },
        {
          "x": -688.626,
          "z": 704.555
        },
        {
          "x": -691.488,
          "z": 704.533
        },
        {
          "x": -691.506,
          "z": 707.305
        },
        {
          "x": -693.214,
          "z": 707.294
        },
        {
          "x": -693.26,
          "z": 713.127
        },
        {
          "x": -682.516,
          "z": 714.886
        },
        {
          "x": -677.596,
          "z": 715.097
        },
        {
          "x": -677.532,
          "z": 707.127
        }
      ],
      "height_m": 7.0,
      "id": "way/411123560",
      "levels": 0,
      "name": null
    },
    {
      "building": "house",
      "footprint": [
        {
          "x": -627.745,
          "z": 578.552
        },
        {
          "x": -627.791,
          "z": 568.01
        },
        {
          "x": -633.606,
          "z": 568.044
        },
        {
          "x": -633.606,
          "z": 567.287
        },
        {
          "x": -635.535,
          "z": 567.298
        },
        {
          "x": -635.526,
          "z": 568.099
        },
        {
          "x": -637.012,
          "z": 568.11
        },
        {
          "x": -637.012,
          "z": 567.821
        },
        {
          "x": -640.879,
          "z": 567.832
        },
        {
          "x": -640.861,
          "z": 570.37
        },
        {
          "x": -643.011,
          "z": 570.381
        },
        {
          "x": -642.993,
          "z": 574.144
        },
        {
          "x": -641.858,
          "z": 574.144
        },
        {
          "x": -641.839,
          "z": 578.608
        },
        {
          "x": -627.745,
          "z": 578.552
        }
      ],
      "height_m": 4.6,
      "id": "way/411123564",
      "levels": 0,
      "name": null
    },
    {
      "building": "house",
      "footprint": [
        {
          "x": -689.134,
          "z": 683.483
        },
        {
          "x": -689.125,
          "z": 682.826
        },
        {
          "x": -685.617,
          "z": 682.87
        },
        {
          "x": -685.627,
          "z": 683.349
        },
        {
          "x": -678.298,
          "z": 683.449
        },
        {
          "x": -678.224,
          "z": 678.273
        },
        {
          "x": -683.79,
          "z": 678.195
        },
        {
          "x": -683.67,
          "z": 669.178
        },
        {
          "x": -687.463,
          "z": 669.122
        },
        {
          "x": -687.509,
          "z": 671.983
        },
        {
          "x": -695.364,
          "z": 671.872
        },
        {
          "x": -695.401,
          "z": 674.276
        },
        {
          "x": -696.786,
          "z": 674.254
        },
        {
          "x": -696.906,
          "z": 683.371
        },
        {
          "x": -689.134,
          "z": 683.483
        }
      ],
      "height_m": 8.2,
      "id": "way/411123567",
      "levels": 0,
      "name": null
    },
    {
      "building": "house",
      "footprint": [
        {
          "x": -692.697,
          "z": 697.676
        },
        {
          "x": -685.719,
          "z": 697.743
        },
        {
          "x": -685.737,
          "z": 698.789
        },
        {
          "x": -680.688,
          "z": 698.834
        },
        {
          "x": -680.679,
          "z": 697.631
        },
        {
          "x": -679.378,
          "z": 697.654
        },
        {
          "x": -679.341,
          "z": 693.835
        },
        {
          "x": -677.606,
          "z": 693.858
        },
        {
          "x": -677.596,
          "z": 692.143
        },
        {
          "x": -676.96,
          "z": 692.143
        },
        {
          "x": -676.913,
          "z": 688.336
        },
        {
          "x": -687.399,
          "z": 688.225
        },
        {
          "x": -687.399,
          "z": 687.869
        },
        {
          "x": -692.595,
          "z": 687.813
        },
        {
          "x": -692.697,
          "z": 697.676
        }
      ],
      "height_m": 4.1,
      "id": "way/411123583",
      "levels": 0,
      "name": null
    },
    {
      "building": "house",
      "footprint": [
        {
          "x": -623.767,
          "z": 594.605
        },
        {
          "x": -623.711,
          "z": 588.649
        },
        {
          "x": -628.105,
          "z": 588.605
        },
        {
          "x": -628.05,
          "z": 582.404
        },
        {
          "x": -632.895,
          "z": 582.359
        },
        {
          "x": -632.905,
          "z": 582.883
        },
        {
          "x": -639.652,
          "z": 582.816
        },
        {
          "x": -639.624,
          "z": 579.588
        },
        {
          "x": -640.842,
          "z": 579.576
        },
        {
          "x": -640.889,
          "z": 588.426
        },
        {
          "x": -643.067,
          "z": 588.382
        },
        {
          "x": -643.113,
          "z": 593.369
        },
        {
          "x": -638.23,
          "z": 593.414
        },
        {
          "x": -638.249,
          "z": 594.46
        },
        {
          "x": -623.767,
          "z": 594.605
        }
      ],
      "height_m": 7.2,
      "id": "way/411123596",
      "levels": 0,
      "name": null
    },
    {
      "building": "apartments",
      "footprint": [
        {
          "x": -596.178,
          "z": 681.323
        },
        {
          "x": -595.818,
          "z": 681.323
        },
        {
          "x": -595.818,
          "z": 685.798
        },
        {
          "x": -597.027,
          "z": 685.798
        },
        {
          "x": -597.027,
          "z": 690.062
        },
        {
          "x": -593.261,
          "z": 690.062
        },
        {
          "x": -593.261,
          "z": 691.208
        },
        {
          "x": -590.456,
          "z": 691.219
        },
        {
          "x": -590.456,
          "z": 691.576
        },
        {
          "x": -583.653,
          "z": 691.576
        },
        {
          "x": -583.653,
          "z": 685.431
        },
        {
          "x": -586.431,
          "z": 685.431
        },
        {
          "x": -586.422,
          "z": 678.707
        },
        {
          "x": -596.178,
          "z": 678.707
        },
        {
          "x": -596.178,
          "z": 681.323
        }
      ],
      "height_m": 7.5,
      "id": "way/411123610",
      "levels": 0,
      "name": null
    },
    {
      "building": "house",
      "footprint": [
        {
          "x": -626.573,
          "z": 715.52
        },
        {
          "x": -626.277,
          "z": 715.532
        },
        {
          "x": -626.185,
          "z": 711.969
        },
        {
          "x": -632.055,
          "z": 711.802
        },
        {
          "x": -632.009,
          "z": 710.077
        },
        {
          "x": -640.575,
          "z": 709.843
        },
        {
          "x": -640.602,
          "z": 710.7
        },
        {
          "x": -646.519,
          "z": 710.544
        },
        {
          "x": -646.805,
          "z": 721.075
        },
        {
          "x": -642.91,
          "z": 721.187
        },
        {
          "x": -642.928,
          "z": 721.599
        },
        {
          "x": -631.88,
          "z": 721.899
        },
        {
          "x": -631.862,
          "z": 721.265
        },
        {
          "x": -626.73,
          "z": 721.398
        },
        {
          "x": -626.573,
          "z": 715.52
        }
      ],
      "height_m": 9.2,
      "id": "way/411123612",
      "levels": 0,
      "name": null
    },
    {
      "building": "residential",
      "footprint": [
        {
          "x": -597.923,
          "z": 655.597
        },
        {
          "x": -597.941,
          "z": 656.821
        },
        {
          "x": -593.068,
          "z": 656.899
        },
        {
          "x": -593.031,
          "z": 654.428
        },
        {
          "x": -583.45,
          "z": 654.573
        },
        {
          "x": -583.395,
          "z": 650.988
        },
        {
          "x": -583.145,
          "z": 650.988
        },
        {
          "x": -583.127,
          "z": 649.708
        },
        {
          "x": -584.77,
          "z": 649.675
        },
        {
          "x": -584.678,
          "z": 643.697
        },
        {
          "x": -591.314,
          "z": 643.597
        },
        {
          "x": -591.379,
          "z": 648.15
        },
        {
          "x": -603.387,
          "z": 647.971
        },
        {
          "x": -603.442,
          "z": 651.6
        },
        {
          "x": -605.63,
          "z": 651.567
        },
        {
          "x": -605.685,
          "z": 655.486
        },
        {
          "x": -597.923,
          "z": 655.597
        }
      ],
      "height_m": 4.4,
      "id": "way/411123630",
      "levels": 0,
      "name": null
    },
    {
      "building": "apartments",
      "footprint": [
        {
          "x": -603.793,
          "z": 679.33
        },
        {
          "x": -603.784,
          "z": 678.985
        },
        {
          "x": -605.944,
          "z": 678.952
        },
        {
          "x": -605.944,
          "z": 679.341
        },
        {
          "x": -612.691,
          "z": 679.23
        },
        {
          "x": -612.811,
          "z": 686.655
        },
        {
          "x": -609.063,
          "z": 686.722
        },
        {
          "x": -609.082,
          "z": 687.779
        },
        {
          "x": -607.485,
          "z": 687.813
        },
        {
          "x": -607.466,
          "z": 686.744
        },
        {
          "x": -601.744,
          "z": 686.844
        },
        {
          "x": -601.698,
          "z": 683.939
        },
        {
          "x": -600.202,
          "z": 683.961
        },
        {
          "x": -600.166,
          "z": 682.258
        },
        {
          "x": -601.799,
          "z": 682.236
        },
        {
          "x": -601.753,
          "z": 679.364
        },
        {
          "x": -603.793,
          "z": 679.33
        }
      ],
      "height_m": 7.3,
      "id": "way/411123657",
      "levels": 0,
      "name": null
    },
    {
      "building": "house",
      "footprint": [
        {
          "x": -597.193,
          "z": 584.608
        },
        {
          "x": -597.24,
          "z": 591.632
        },
        {
          "x": -598.301,
          "z": 591.621
        },
        {
          "x": -598.32,
          "z": 594.415
        },
        {
          "x": -597.037,
          "z": 594.427
        },
        {
          "x": -597.027,
          "z": 593.814
        },
        {
          "x": -591.388,
          "z": 593.859
        },
        {
          "x": -591.397,
          "z": 594.516
        },
        {
          "x": -588.619,
          "z": 594.538
        },
        {
          "x": -588.61,
          "z": 593.837
        },
        {
          "x": -584.945,
          "z": 593.87
        },
        {
          "x": -584.927,
          "z": 590.864
        },
        {
          "x": -583.118,
          "z": 590.875
        },
        {
          "x": -583.099,
          "z": 587.703
        },
        {
          "x": -584.862,
          "z": 587.692
        },
        {
          "x": -584.834,
          "z": 584.697
        },
        {
          "x": -597.193,
          "z": 584.608
        }
      ],
      "height_m": 4.2,
      "id": "way/411123662",
      "levels": 0,
      "name": null
    },
    {
      "building": "house",
      "footprint": [
        {
          "x": -683.873,
          "z": 621.366
        },
        {
          "x": -683.873,
          "z": 621.611
        },
        {
          "x": -680.781,
          "z": 621.622
        },
        {
          "x": -680.772,
          "z": 616.768
        },
        {
          "x": -682.442,
          "z": 616.757
        },
        {
          "x": -682.433,
          "z": 613.574
        },
        {
          "x": -680.495,
          "z": 613.585
        },
        {
          "x": -680.485,
          "z": 610.612
        },
        {
          "x": -683.974,
          "z": 610.601
        },
        {
          "x": -683.974,
          "z": 610.846
        },
        {
          "x": -690.518,
          "z": 610.813
        },
        {
          "x": -690.528,
          "z": 612.249
        },
        {
          "x": -692.771,
          "z": 612.249
        },
        {
          "x": -692.78,
          "z": 615.455
        },
        {
          "x": -697.459,
          "z": 615.444
        },
        {
          "x": -697.478,
          "z": 621.31
        },
        {
          "x": -683.873,
          "z": 621.366
        }
      ],
      "height_m": 4.3,
      "id": "way/411123664",
      "levels": 0,
      "name": null
    },
    {
      "building": "house",
      "footprint": [
        {
          "x": -682.359,
          "z": 648.873
        },
        {
          "x": -680.402,
          "z": 648.895
        },
        {
          "x": -680.375,
          "z": 646.357
        },
        {
          "x": -681.215,
          "z": 646.346
        },
        {
          "x": -681.159,
          "z": 641.994
        },
        {
          "x": -683.218,
          "z": 641.96
        },
        {
          "x": -683.208,
          "z": 641.381
        },
        {
          "x": -684.353,
          "z": 641.37
        },
        {
          "x": -684.353,
          "z": 641.982
        },
        {
          "x": -694.257,
          "z": 641.849
        },
        {
          "x": -694.247,
          "z": 641.548
        },
        {
          "x": -698.216,
          "z": 641.493
        },
        {
          "x": -698.309,
          "z": 648.717
        },
        {
          "x": -699.509,
          "z": 648.695
        },
        {
          "x": -699.555,
          "z": 652.447
        },
        {
          "x": -694.33,
          "z": 652.513
        },
        {
          "x": -694.33,
          "z": 652.213
        },
        {
          "x": -682.405,
          "z": 652.369
        },
        {
          "x": -682.359,
          "z": 648.873
        }
      ],
      "height_m": 4.6,
      "id": "way/411123671",
      "levels": 0,
      "name": null
    },
    {
      "building": "apartments",
      "footprint": [
        {
          "x": -625.788,
          "z": 690.796
        },
        {
          "x": -625.779,
          "z": 688.158
        },
        {
          "x": -623.794,
          "z": 688.158
        },
        {
          "x": -623.767,
          "z": 679.163
        },
        {
          "x": -626.803,
          "z": 679.152
        },
        {
          "x": -626.794,
          "z": 678.273
        },
        {
          "x": -630.514,
          "z": 678.262
        },
        {
          "x": -630.514,
          "z": 679.141
        },
        {
          "x": -630.92,
          "z": 679.141
        },
        {
          "x": -630.92,
          "z": 681.089
        },
        {
          "x": -632.969,
          "z": 681.089
        },
        {
          "x": -632.978,
          "z": 682.547
        },
        {
          "x": -638.812,
          "z": 682.536
        },
        {
          "x": -638.812,
          "z": 682.069
        },
        {
          "x": -640.556,
          "z": 682.058
        },
        {
          "x": -640.565,
          "z": 682.525
        },
        {
          "x": -643.085,
          "z": 682.525
        },
        {
          "x": -643.104,
          "z": 690.752
        },
        {
          "x": -625.788,
          "z": 690.796
        }
      ],
      "height_m": 7.5,
      "id": "way/411123678",
      "levels": 0,
      "name": null
    },
    {
      "building": "house",
      "footprint": [
        {
          "x": -601.402,
          "z": 578.986
        },
        {
          "x": -593.889,
          "z": 578.897
        },
        {
          "x": -593.889,
          "z": 578.441
        },
        {
          "x": -592.237,
          "z": 578.43
        },
        {
          "x": -592.218,
          "z": 579.61
        },
        {
          "x": -586.874,
          "z": 579.554
        },
        {
          "x": -586.874,
          "z": 579.02
        },
        {
          "x": -582.684,
          "z": 578.975
        },
        {
          "x": -582.776,
          "z": 571.339
        },
        {
          "x": -584.788,
          "z": 571.361
        },
        {
          "x": -584.825,
          "z": 568.344
        },
        {
          "x": -586.847,
          "z": 568.367
        },
        {
          "x": -586.847,
          "z": 568.845
        },
        {
          "x": -589.126,
          "z": 568.867
        },
        {
          "x": -589.136,
          "z": 568.155
        },
        {
          "x": -596.612,
          "z": 568.233
        },
        {
          "x": -596.575,
          "z": 571.261
        },
        {
          "x": -601.495,
          "z": 571.317
        },
        {
          "x": -601.402,
          "z": 578.986
        }
      ],
      "height_m": 4.1,
      "id": "way/411123687",
      "levels": 0,
      "name": null
    },
    {
      "building": "house",
      "footprint": [
        {
          "x": -637.169,
          "z": 603.354
        },
        {
          "x": -642.688,
          "z": 603.343
        },
        {
          "x": -642.707,
          "z": 610.1
        },
        {
          "x": -641.996,
          "z": 610.1
        },
        {
          "x": -641.996,
          "z": 608.854
        },
        {
          "x": -636.597,
          "z": 608.865
        },
        {
          "x": -636.597,
          "z": 608.464
        },
        {
          "x": -631.409,
          "z": 608.475
        },
        {
          "x": -631.418,
          "z": 609.188
        },
        {
          "x": -622.982,
          "z": 609.21
        },
        {
          "x": -622.973,
          "z": 604.969
        },
        {
          "x": -625.659,
          "z": 604.957
        },
        {
          "x": -625.64,
          "z": 600.404
        },
        {
          "x": -624.662,
          "z": 600.416
        },
        {
          "x": -624.653,
          "z": 598.924
        },
        {
          "x": -625.64,
          "z": 598.913
        },
        {
          "x": -625.631,
          "z": 598.256
        },
        {
          "x": -633.246,
          "z": 598.234
        },
        {
          "x": -633.237,
          "z": 595.094
        },
        {
          "x": -637.15,
          "z": 595.083
        },
        {
          "x": -637.169,
          "z": 603.354
        }
      ],
      "height_m": 4.7,
      "id": "way/411123732",
      "levels": 0,
      "name": null
    },
    {
      "building": "house",
      "footprint": [
        {
          "x": -602.759,
          "z": 624.761
        },
        {
          "x": -595.227,
          "z": 624.739
        },
        {
          "x": -595.237,
          "z": 625.04
        },
        {
          "x": -591.342,
          "z": 625.028
        },
        {
          "x": -591.342,
          "z": 625.24
        },
        {
          "x": -583.644,
          "z": 625.229
        },
        {
          "x": -583.635,
          "z": 626.242
        },
        {
          "x": -582.988,
          "z": 626.242
        },
        {
          "x": -583.007,
          "z": 617.603
        },
        {
          "x": -583.644,
          "z": 617.614
        },
        {
          "x": -583.635,
          "z": 618.127
        },
        {
          "x": -590.631,
          "z": 618.149
        },
        {
          "x": -590.64,
          "z": 614.286
        },
        {
          "x": -589.274,
          "z": 614.286
        },
        {
          "x": -589.283,
          "z": 610.657
        },
        {
          "x": -595.366,
          "z": 610.679
        },
        {
          "x": -595.357,
          "z": 613.64
        },
        {
          "x": -601.476,
          "z": 613.663
        },
        {
          "x": -601.476,
          "z": 616.067
        },
        {
          "x": -602.778,
          "z": 616.067
        },
        {
          "x": -602.759,
          "z": 624.761
        }
      ],
      "height_m": 6.0,
      "id": "way/411123748",
      "levels": 0,
      "name": null
    },
    {
      "building": "house",
      "footprint": [
        {
          "x": -681.593,
          "z": 606.56
        },
        {
          "x": -681.575,
          "z": 602.92
        },
        {
          "x": -679.23,
          "z": 602.943
        },
        {
          "x": -679.202,
          "z": 599.069
        },
        {
          "x": -681.547,
          "z": 599.057
        },
        {
          "x": -681.528,
          "z": 595.595
        },
        {
          "x": -681.888,
          "z": 595.584
        },
        {
          "x": -681.888,
          "z": 595.139
        },
        {
          "x": -684.528,
          "z": 595.128
        },
        {
          "x": -684.528,
          "z": 595.573
        },
        {
          "x": -690.703,
          "z": 595.529
        },
        {
          "x": -690.712,
          "z": 596.486
        },
        {
          "x": -692.106,
          "z": 596.475
        },
        {
          "x": -692.106,
          "z": 595.35
        },
        {
          "x": -697.644,
          "z": 595.317
        },
        {
          "x": -697.672,
          "z": 600.26
        },
        {
          "x": -692.189,
          "z": 600.293
        },
        {
          "x": -692.18,
          "z": 598.122
        },
        {
          "x": -690.722,
          "z": 598.133
        },
        {
          "x": -690.777,
          "z": 606.505
        },
        {
          "x": -681.593,
          "z": 606.56
        }
      ],
      "height_m": 4.7,
      "id": "way/411123755",
      "levels": 0,
      "name": null
    },
    {
      "building": "apartments",
      "footprint": [
        {
          "x": -623.49,
          "z": 655.842
        },
        {
          "x": -623.416,
          "z": 650.287
        },
        {
          "x": -622.687,
          "z": 650.298
        },
        {
          "x": -622.631,
          "z": 646.09
        },
        {
          "x": -630.339,
          "z": 645.99
        },
        {
          "x": -630.274,
          "z": 641.103
        },
        {
          "x": -639.199,
          "z": 640.981
        },
        {
          "x": -639.209,
          "z": 641.381
        },
        {
          "x": -639.726,
          "z": 641.381
        },
        {
          "x": -639.753,
          "z": 643.329
        },
        {
          "x": -642.495,
          "z": 643.296
        },
        {
          "x": -642.578,
          "z": 649.508
        },
        {
          "x": -643.279,
          "z": 649.497
        },
        {
          "x": -643.298,
          "z": 650.565
        },
        {
          "x": -643.805,
          "z": 650.565
        },
        {
          "x": -643.842,
          "z": 653.326
        },
        {
          "x": -643.334,
          "z": 653.337
        },
        {
          "x": -643.344,
          "z": 654.361
        },
        {
          "x": -636.717,
          "z": 654.45
        },
        {
          "x": -636.735,
          "z": 655.653
        },
        {
          "x": -623.49,
          "z": 655.842
        }
      ],
      "height_m": 8.1,
      "id": "way/411123759",
      "levels": 0,
      "name": null
    },
    {
      "building": "house",
      "footprint": [
        {
          "x": -595.311,
          "z": 598.757
        },
        {
          "x": -595.311,
          "z": 599.091
        },
        {
          "x": -595.634,
          "z": 599.091
        },
        {
          "x": -595.634,
          "z": 601.083
        },
        {
          "x": -596.769,
          "z": 601.083
        },
        {
          "x": -596.769,
          "z": 605.269
        },
        {
          "x": -595.67,
          "z": 605.269
        },
        {
          "x": -595.661,
          "z": 609.41
        },
        {
          "x": -593.788,
          "z": 609.41
        },
        {
          "x": -593.788,
          "z": 610.39
        },
        {
          "x": -587.65,
          "z": 610.39
        },
        {
          "x": -587.65,
          "z": 609.488
        },
        {
          "x": -584.807,
          "z": 609.488
        },
        {
          "x": -584.816,
          "z": 604.879
        },
        {
          "x": -585.287,
          "z": 604.879
        },
        {
          "x": -585.287,
          "z": 603.722
        },
        {
          "x": -584.604,
          "z": 603.711
        },
        {
          "x": -584.604,
          "z": 601.395
        },
        {
          "x": -585.084,
          "z": 601.395
        },
        {
          "x": -585.084,
          "z": 599.213
        },
        {
          "x": -589.117,
          "z": 599.213
        },
        {
          "x": -589.117,
          "z": 598.757
        },
        {
          "x": -595.311,
          "z": 598.757
        }
      ],
      "height_m": 7.7,
      "id": "way/411123791",
      "levels": 0,
      "name": null
    },
    {
      "building": "house",
      "footprint": [
        {
          "x": -679.239,
          "z": 591.209
        },
        {
          "x": -679.23,
          "z": 589.707
        },
        {
          "x": -678.233,
          "z": 589.718
        },
        {
          "x": -678.206,
          "z": 586.523
        },
        {
          "x": -679.202,
          "z": 586.512
        },
        {
          "x": -679.193,
          "z": 585.142
        },
        {
          "x": -680.596,
          "z": 585.131
        },
        {
          "x": -680.559,
          "z": 581.625
        },
        {
          "x": -682.165,
          "z": 581.614
        },
        {
          "x": -682.156,
          "z": 581.269
        },
        {
          "x": -684.74,
          "z": 581.246
        },
        {
          "x": -684.74,
          "z": 581.001
        },
        {
          "x": -685.543,
          "z": 581.001
        },
        {
          "x": -685.543,
          "z": 580.712
        },
        {
          "x": -688.313,
          "z": 580.69
        },
        {
          "x": -688.313,
          "z": 580.979
        },
        {
          "x": -688.996,
          "z": 580.968
        },
        {
          "x": -688.996,
          "z": 581.335
        },
        {
          "x": -691.045,
          "z": 581.313
        },
        {
          "x": -691.045,
          "z": 581.636
        },
        {
          "x": -693.509,
          "z": 581.614
        },
        {
          "x": -693.583,
          "z": 591.087
        },
        {
          "x": -679.239,
          "z": 591.209
        }
      ],
      "height_m": 5.7,
      "id": "way/411123800",
      "levels": 0,
      "name": null
    },
    {
      "building": "residential",
      "footprint": [
        {
          "x": -697.432,
          "z": 569.346
        },
        {
          "x": -701.696,
          "z": 569.324
        },
        {
          "x": -701.724,
          "z": 573.454
        },
        {
          "x": -696.287,
          "z": 573.487
        },
        {
          "x": -696.306,
          "z": 575.725
        },
        {
          "x": -691.866,
          "z": 575.758
        },
        {
          "x": -691.866,
          "z": 575.536
        },
        {
          "x": -690.509,
          "z": 575.524
        },
        {
          "x": -690.039,
          "z": 575.235
        },
        {
          "x": -689.872,
          "z": 575.012
        },
        {
          "x": -689.762,
          "z": 574.823
        },
        {
          "x": -689.78,
          "z": 574.545
        },
        {
          "x": -684.344,
          "z": 574.589
        },
        {
          "x": -684.344,
          "z": 574.1
        },
        {
          "x": -683.014,
          "z": 574.1
        },
        {
          "x": -682.571,
          "z": 573.877
        },
        {
          "x": -682.193,
          "z": 573.32
        },
        {
          "x": -682.138,
          "z": 572.975
        },
        {
          "x": -679.036,
          "z": 572.997
        },
        {
          "x": -678.99,
          "z": 566.318
        },
        {
          "x": -686.688,
          "z": 566.274
        },
        {
          "x": -686.697,
          "z": 567.454
        },
        {
          "x": -697.413,
          "z": 567.376
        },
        {
          "x": -697.432,
          "z": 569.346
        }
      ],
      "height_m": 5.0,
      "id": "way/411123809",
      "levels": 0,
      "name": null
    },
    {
      "building": "residential",
      "footprint": [
        {
          "x": -613.106,
          "z": 707.461
        },
        {
          "x": -603.747,
          "z": 707.472
        },
        {
          "x": -603.747,
          "z": 707.116
        },
        {
          "x": -596.326,
          "z": 707.127
        },
        {
          "x": -596.335,
          "z": 706.682
        },
        {
          "x": -583.256,
          "z": 706.693
        },
        {
          "x": -583.247,
          "z": 700.047
        },
        {
          "x": -585.074,
          "z": 700.047
        },
        {
          "x": -585.074,
          "z": 698.967
        },
        {
          "x": -587.077,
          "z": 698.967
        },
        {
          "x": -587.068,
          "z": 696.218
        },
        {
          "x": -593.917,
          "z": 696.206
        },
        {
          "x": -593.917,
          "z": 694.915
        },
        {
          "x": -596.114,
          "z": 694.915
        },
        {
          "x": -596.104,
          "z": 695.672
        },
        {
          "x": -600.387,
          "z": 695.672
        },
        {
          "x": -600.387,
          "z": 695.95
        },
        {
          "x": -601.864,
          "z": 695.95
        },
        {
          "x": -601.873,
          "z": 701.672
        },
        {
          "x": -604.116,
          "z": 701.672
        },
        {
          "x": -604.116,
          "z": 700.57
        },
        {
          "x": -611.805,
          "z": 700.559
        },
        {
          "x": -611.805,
          "z": 701.572
        },
        {
          "x": -613.097,
          "z": 701.572
        },
        {
          "x": -613.106,
          "z": 707.461
        }
      ],
      "height_m": 7.5,
      "id": "way/411123810",
      "levels": 0,
      "name": null
    },
    {
      "building": "house",
      "footprint": [
        {
          "x": -582.601,
          "z": 555.798
        },
        {
          "x": -582.37,
          "z": 555.798
        },
        {
          "x": -582.305,
          "z": 552.748
        },
        {
          "x": -583.339,
          "z": 552.726
        },
        {
          "x": -583.339,
          "z": 552.459
        },
        {
          "x": -583.967,
          "z": 552.448
        },
        {
          "x": -583.911,
          "z": 549.453
        },
        {
          "x": -588.49,
          "z": 549.353
        },
        {
          "x": -588.563,
          "z": 552.592
        },
        {
          "x": -599.206,
          "z": 552.37
        },
        {
          "x": -599.261,
          "z": 554.752
        },
        {
          "x": -599.732,
          "z": 555.042
        },
        {
          "x": -600.286,
          "z": 554.129
        },
        {
          "x": -601.836,
          "z": 555.075
        },
        {
          "x": -601.329,
          "z": 555.921
        },
        {
          "x": -603.267,
          "z": 557.101
        },
        {
          "x": -603.488,
          "z": 556.734
        },
        {
          "x": -605.085,
          "z": 557.713
        },
        {
          "x": -604.827,
          "z": 558.147
        },
        {
          "x": -606.793,
          "z": 559.35
        },
        {
          "x": -606.839,
          "z": 563.68
        },
        {
          "x": -598.892,
          "z": 563.747
        },
        {
          "x": -598.892,
          "z": 564.136
        },
        {
          "x": -582.785,
          "z": 564.281
        },
        {
          "x": -582.601,
          "z": 555.798
        }
      ],
      "height_m": 5.5,
      "id": "way/411123816",
      "levels": 0,
      "name": null
    },
    {
      "building": "residential",
      "footprint": [
        {
          "x": -598.993,
          "z": 641.114
        },
        {
          "x": -598.984,
          "z": 639.912
        },
        {
          "x": -596.206,
          "z": 639.923
        },
        {
          "x": -596.197,
          "z": 639.088
        },
        {
          "x": -595.126,
          "z": 639.088
        },
        {
          "x": -595.135,
          "z": 640.212
        },
        {
          "x": -593.28,
          "z": 640.224
        },
        {
          "x": -593.271,
          "z": 639.099
        },
        {
          "x": -592.468,
          "z": 639.099
        },
        {
          "x": -592.468,
          "z": 640.101
        },
        {
          "x": -584.53,
          "z": 640.135
        },
        {
          "x": -584.539,
          "z": 641.17
        },
        {
          "x": -582.527,
          "z": 641.181
        },
        {
          "x": -582.49,
          "z": 632.687
        },
        {
          "x": -583.773,
          "z": 632.676
        },
        {
          "x": -583.764,
          "z": 629.604
        },
        {
          "x": -594.083,
          "z": 629.559
        },
        {
          "x": -594.074,
          "z": 629.092
        },
        {
          "x": -598.218,
          "z": 629.069
        },
        {
          "x": -599.39,
          "z": 634.802
        },
        {
          "x": -606.322,
          "z": 634.78
        },
        {
          "x": -606.322,
          "z": 635.815
        },
        {
          "x": -608.639,
          "z": 635.804
        },
        {
          "x": -608.648,
          "z": 637.953
        },
        {
          "x": -611.159,
          "z": 637.942
        },
        {
          "x": -611.168,
          "z": 641.058
        },
        {
          "x": -598.993,
          "z": 641.114
        }
      ],
      "height_m": 4.5,
      "id": "way/411123827",
      "levels": 0,
      "name": null
    },
    {
      "building": "residential",
      "footprint": [
        {
          "x": -686.605,
          "z": 560.83
        },
        {
          "x": -686.614,
          "z": 561.498
        },
        {
          "x": -681.067,
          "z": 561.565
        },
        {
          "x": -680.993,
          "z": 555.832
        },
        {
          "x": -679.719,
          "z": 555.854
        },
        {
          "x": -679.719,
          "z": 555.309
        },
        {
          "x": -678.409,
          "z": 555.331
        },
        {
          "x": -678.372,
          "z": 553.027
        },
        {
          "x": -677.781,
          "z": 553.027
        },
        {
          "x": -677.726,
          "z": 549.041
        },
        {
          "x": -679.618,
          "z": 549.019
        },
        {
          "x": -679.618,
          "z": 548.663
        },
        {
          "x": -687.251,
          "z": 548.563
        },
        {
          "x": -687.26,
          "z": 549.13
        },
        {
          "x": -699.795,
          "z": 548.986
        },
        {
          "x": -699.804,
          "z": 549.542
        },
        {
          "x": -700.958,
          "z": 549.531
        },
        {
          "x": -701.004,
          "z": 553.06
        },
        {
          "x": -699.85,
          "z": 553.071
        },
        {
          "x": -699.878,
          "z": 555.019
        },
        {
          "x": -698.733,
          "z": 555.03
        },
        {
          "x": -698.752,
          "z": 556.745
        },
        {
          "x": -701.447,
          "z": 556.711
        },
        {
          "x": -701.428,
          "z": 555.119
        },
        {
          "x": -708.84,
          "z": 555.03
        },
        {
          "x": -708.905,
          "z": 560.563
        },
        {
          "x": -686.605,
          "z": 560.83
        }
      ],
      "height_m": 4.7,
      "id": "way/411123829",
      "levels": 0,
      "name": null
    },
    {
      "building": "house",
      "footprint": [
        {
          "x": -617.13,
          "z": 633.133
        },
        {
          "x": -620.665,
          "z": 633.099
        },
        {
          "x": -620.647,
          "z": 630.984
        },
        {
          "x": -623.305,
          "z": 630.962
        },
        {
          "x": -623.296,
          "z": 630.127
        },
        {
          "x": -630.071,
          "z": 630.071
        },
        {
          "x": -630.071,
          "z": 630.728
        },
        {
          "x": -631.197,
          "z": 630.717
        },
        {
          "x": -631.206,
          "z": 631.207
        },
        {
          "x": -632.175,
          "z": 629.982
        },
        {
          "x": -632.72,
          "z": 629.648
        },
        {
          "x": -633.606,
          "z": 629.57
        },
        {
          "x": -634.114,
          "z": 629.726
        },
        {
          "x": -634.566,
          "z": 630.027
        },
        {
          "x": -634.898,
          "z": 630.361
        },
        {
          "x": -635.24,
          "z": 631.173
        },
        {
          "x": -639.818,
          "z": 631.14
        },
        {
          "x": -639.846,
          "z": 633.711
        },
        {
          "x": -641.248,
          "z": 633.7
        },
        {
          "x": -641.276,
          "z": 637.073
        },
        {
          "x": -643.676,
          "z": 637.062
        },
        {
          "x": -643.704,
          "z": 640.836
        },
        {
          "x": -639.439,
          "z": 640.88
        },
        {
          "x": -639.43,
          "z": 639.956
        },
        {
          "x": -635.867,
          "z": 639.99
        },
        {
          "x": -635.877,
          "z": 640.669
        },
        {
          "x": -629.351,
          "z": 640.725
        },
        {
          "x": -629.342,
          "z": 639.979
        },
        {
          "x": -617.186,
          "z": 640.079
        },
        {
          "x": -617.13,
          "z": 633.133
        }
      ],
      "height_m": 7.1,
      "id": "way/411123878",
      "levels": 0,
      "name": null
    },
    {
      "building": "apartments",
      "footprint": [
        {
          "x": -613.272,
          "z": 655.808
        },
        {
          "x": -613.245,
          "z": 649.229
        },
        {
          "x": -622.41,
          "z": 649.207
        },
        {
          "x": -622.438,
          "z": 655.786
        },
        {
          "x": -613.272,
          "z": 655.808
        }
      ],
      "height_m": 5.5,
      "id": "way/411123901",
      "levels": 0,
      "name": null
    },
    {
      "building": "house",
      "footprint": [
        {
          "x": -608.094,
          "z": 591.877
        },
        {
          "x": -612.691,
          "z": 591.844
        },
        {
          "x": -612.709,
          "z": 594.95
        },
        {
          "x": -608.113,
          "z": 594.983
        },
        {
          "x": -608.094,
          "z": 591.877
        }
      ],
      "height_m": 2.9,
      "id": "way/411123902",
      "levels": 0,
      "name": null
    },
    {
      "building": "house",
      "footprint": [
        {
          "x": -612.894,
          "z": 544.444
        },
        {
          "x": -617.103,
          "z": 544.466
        },
        {
          "x": -617.066,
          "z": 549.286
        },
        {
          "x": -612.866,
          "z": 549.253
        },
        {
          "x": -612.894,
          "z": 544.444
        }
      ],
      "height_m": 3.3,
      "id": "way/411123905",
      "levels": 0,
      "name": null
    },
    {
      "building": "house",
      "footprint": [
        {
          "x": -614.814,
          "z": 711.669
        },
        {
          "x": -614.786,
          "z": 707.973
        },
        {
          "x": -620.536,
          "z": 707.917
        },
        {
          "x": -620.573,
          "z": 711.613
        },
        {
          "x": -614.814,
          "z": 711.669
        }
      ],
      "height_m": 3.6,
      "id": "way/411123922",
      "levels": 0,
      "name": null
    },
    {
      "building": "house",
      "footprint": [
        {
          "x": -704.908,
          "z": 714.051
        },
        {
          "x": -709.92,
          "z": 711.769
        },
        {
          "x": -712.32,
          "z": 717.068
        },
        {
          "x": -707.308,
          "z": 719.35
        },
        {
          "x": -704.908,
          "z": 714.051
        }
      ],
      "height_m": 3.8,
      "id": "way/411123923",
      "levels": 0,
      "name": null
    },
    {
      "building": "house",
      "footprint": [
        {
          "x": -599.123,
          "z": 567.966
        },
        {
          "x": -599.104,
          "z": 565.027
        },
        {
          "x": -604.79,
          "z": 564.982
        },
        {
          "x": -604.808,
          "z": 567.921
        },
        {
          "x": -599.123,
          "z": 567.966
        }
      ],
      "height_m": 4.0,
      "id": "way/411123931",
      "levels": 0,
      "name": null
    },
    {
      "building": "residential",
      "footprint": [
        {
          "x": -707.853,
          "z": 568.879
        },
        {
          "x": -701.493,
          "z": 568.945
        },
        {
          "x": -701.428,
          "z": 562.288
        },
        {
          "x": -707.788,
          "z": 562.233
        },
        {
          "x": -707.853,
          "z": 568.879
        }
      ],
      "height_m": 4.2,
      "id": "way/411123934",
      "levels": 0,
      "name": null
    },
    {
      "building": "house",
      "footprint": [
        {
          "x": -620.389,
          "z": 699.112
        },
        {
          "x": -614.583,
          "z": 699.101
        },
        {
          "x": -614.592,
          "z": 692.41
        },
        {
          "x": -620.398,
          "z": 692.41
        },
        {
          "x": -620.389,
          "z": 699.112
        }
      ],
      "height_m": 6.5,
      "id": "way/411123935",
      "levels": 0,
      "name": null
    },
    {
      "building": "house",
      "footprint": [
        {
          "x": -612.534,
          "z": 616.19
        },
        {
          "x": -606.22,
          "z": 616.223
        },
        {
          "x": -606.193,
          "z": 610.624
        },
        {
          "x": -612.506,
          "z": 610.59
        },
        {
          "x": -612.534,
          "z": 616.19
        }
      ],
      "height_m": 4.0,
      "id": "way/411123940",
      "levels": 0,
      "name": null
    },
    {
      "building": "house",
      "footprint": [
        {
          "x": -622.493,
          "z": 570.381
        },
        {
          "x": -616.484,
          "z": 570.359
        },
        {
          "x": -616.493,
          "z": 564.96
        },
        {
          "x": -622.502,
          "z": 564.982
        },
        {
          "x": -622.493,
          "z": 570.381
        }
      ],
      "height_m": 3.7,
      "id": "way/411123944",
      "levels": 0,
      "name": null
    },
    {
      "building": "house",
      "footprint": [
        {
          "x": -705.545,
          "z": 719.294
        },
        {
          "x": -699.25,
          "z": 721.932
        },
        {
          "x": -696.62,
          "z": 715.598
        },
        {
          "x": -702.905,
          "z": 712.949
        },
        {
          "x": -705.545,
          "z": 719.294
        }
      ],
      "height_m": 5.1,
      "id": "way/411123951",
      "levels": 0,
      "name": null
    },
    {
      "building": "house",
      "footprint": [
        {
          "x": -606.184,
          "z": 549.42
        },
        {
          "x": -612.561,
          "z": 549.398
        },
        {
          "x": -612.589,
          "z": 556.555
        },
        {
          "x": -606.211,
          "z": 556.578
        },
        {
          "x": -606.184,
          "z": 549.42
        }
      ],
      "height_m": 4.4,
      "id": "way/411123957",
      "levels": 0,
      "name": null
    },
    {
      "building": "house",
      "footprint": [
        {
          "x": -709.375,
          "z": 583.027
        },
        {
          "x": -709.228,
          "z": 576.994
        },
        {
          "x": -715.855,
          "z": 576.827
        },
        {
          "x": -715.993,
          "z": 582.86
        },
        {
          "x": -709.375,
          "z": 583.027
        }
      ],
      "height_m": 4.6,
      "id": "way/411123961",
      "levels": 0,
      "name": null
    },
    {
      "building": "house",
      "footprint": [
        {
          "x": -615.091,
          "z": 722.734
        },
        {
          "x": -613.171,
          "z": 722.689
        },
        {
          "x": -613.318,
          "z": 715.22
        },
        {
          "x": -615.238,
          "z": 715.253
        },
        {
          "x": -615.091,
          "z": 722.734
        }
      ],
      "height_m": 2.5,
      "id": "way/411123967",
      "levels": 0,
      "name": null
    },
    {
      "building": "house",
      "footprint": [
        {
          "x": -606.663,
          "z": 707.873
        },
        {
          "x": -612.202,
          "z": 707.739
        },
        {
          "x": -612.349,
          "z": 713.929
        },
        {
          "x": -606.811,
          "z": 714.062
        },
        {
          "x": -606.663,
          "z": 707.873
        }
      ],
      "height_m": 3.3,
      "id": "way/411123980",
      "levels": 0,
      "name": null
    },
    {
      "building": "house",
      "footprint": [
        {
          "x": -710.658,
          "z": 638.342
        },
        {
          "x": -716.501,
          "z": 638.231
        },
        {
          "x": -716.593,
          "z": 643.463
        },
        {
          "x": -710.76,
          "z": 643.574
        },
        {
          "x": -710.658,
          "z": 638.342
        }
      ],
      "height_m": 5.5,
      "id": "way/411124009",
      "levels": 0,
      "name": null
    },
    {
      "building": "house",
      "footprint": [
        {
          "x": -611.722,
          "z": 595.239
        },
        {
          "x": -611.749,
          "z": 599.436
        },
        {
          "x": -605.814,
          "z": 599.48
        },
        {
          "x": -605.787,
          "z": 595.284
        },
        {
          "x": -611.722,
          "z": 595.239
        }
      ],
      "height_m": 4.4,
      "id": "way/411124046",
      "levels": 0,
      "name": null
    },
    {
      "building": "residential",
      "footprint": [
        {
          "x": -711.526,
          "z": 568.344
        },
        {
          "x": -711.526,
          "z": 561.721
        },
        {
          "x": -718.504,
          "z": 561.721
        },
        {
          "x": -718.504,
          "z": 568.344
        },
        {
          "x": -711.526,
          "z": 568.344
        }
      ],
      "height_m": 4.8,
      "id": "way/411124057",
      "levels": 0,
      "name": null
    },
    {
      "building": "house",
      "footprint": [
        {
          "x": -706.523,
          "z": 675.189
        },
        {
          "x": -700.948,
          "z": 675.134
        },
        {
          "x": -701.013,
          "z": 669.089
        },
        {
          "x": -706.579,
          "z": 669.145
        },
        {
          "x": -706.523,
          "z": 675.189
        }
      ],
      "height_m": 3.6,
      "id": "way/411124062",
      "levels": 0,
      "name": null
    },
    {
      "building": "house",
      "footprint": [
        {
          "x": -710.326,
          "z": 596.174
        },
        {
          "x": -710.298,
          "z": 592.434
        },
        {
          "x": -718.366,
          "z": 592.378
        },
        {
          "x": -718.393,
          "z": 596.119
        },
        {
          "x": -710.326,
          "z": 596.174
        }
      ],
      "height_m": 3.3,
      "id": "way/411124086",
      "levels": 0,
      "name": null
    },
    {
      "building": "house",
      "footprint": [
        {
          "x": -614.195,
          "z": 586.167
        },
        {
          "x": -614.14,
          "z": 579.999
        },
        {
          "x": -620.259,
          "z": 579.933
        },
        {
          "x": -620.315,
          "z": 586.1
        },
        {
          "x": -614.195,
          "z": 586.167
        }
      ],
      "height_m": 5.1,
      "id": "way/411124090",
      "levels": 0,
      "name": null
    },
    {
      "building": "house",
      "footprint": [
        {
          "x": -716.123,
          "z": 675.111
        },
        {
          "x": -709.957,
          "z": 675.267
        },
        {
          "x": -709.8,
          "z": 669.044
        },
        {
          "x": -715.966,
          "z": 668.888
        },
        {
          "x": -716.123,
          "z": 675.111
        }
      ],
      "height_m": 3.5,
      "id": "way/411124135",
      "levels": 0,
      "name": null
    },
    {
      "building": "house",
      "footprint": [
        {
          "x": -683.661,
          "z": 722.723
        },
        {
          "x": -682.701,
          "z": 716.177
        },
        {
          "x": -688.682,
          "z": 715.298
        },
        {
          "x": -689.632,
          "z": 721.832
        },
        {
          "x": -683.661,
          "z": 722.723
        }
      ],
      "height_m": 5.7,
      "id": "way/411124154",
      "levels": 0,
      "name": null
    },
    {
      "building": "house",
      "footprint": [
        {
          "x": -709.08,
          "z": 653.337
        },
        {
          "x": -703.237,
          "z": 653.382
        },
        {
          "x": -703.182,
          "z": 646.012
        },
        {
          "x": -709.025,
          "z": 645.968
        },
        {
          "x": -709.08,
          "z": 653.337
        }
      ],
      "height_m": 3.8,
      "id": "way/411124168",
      "levels": 0,
      "name": null
    },
    {
      "building": "house",
      "footprint": [
        {
          "x": -713.243,
          "z": 606.917
        },
        {
          "x": -710.132,
          "z": 607.006
        },
        {
          "x": -710.022,
          "z": 602.853
        },
        {
          "x": -713.132,
          "z": 602.764
        },
        {
          "x": -713.243,
          "z": 606.917
        }
      ],
      "height_m": 3.0,
      "id": "way/411124171",
      "levels": 0,
      "name": null
    },
    {
      "building": "house",
      "footprint": [
        {
          "x": -700.238,
          "z": 659.27
        },
        {
          "x": -700.284,
          "z": 653.782
        },
        {
          "x": -705.822,
          "z": 653.838
        },
        {
          "x": -705.767,
          "z": 659.326
        },
        {
          "x": -700.238,
          "z": 659.27
        }
      ],
      "height_m": 2.9,
      "id": "way/411124174",
      "levels": 0,
      "name": null
    },
    {
      "building": "house",
      "footprint": [
        {
          "x": -701.179,
          "z": 577.361
        },
        {
          "x": -707.76,
          "z": 577.317
        },
        {
          "x": -707.816,
          "z": 585.076
        },
        {
          "x": -701.225,
          "z": 585.109
        },
        {
          "x": -701.179,
          "z": 577.361
        }
      ],
      "height_m": 4.5,
      "id": "way/411124175",
      "levels": 0,
      "name": null
    },
    {
      "building": "house",
      "footprint": [
        {
          "x": -711.628,
          "z": 550.333
        },
        {
          "x": -711.6,
          "z": 546.648
        },
        {
          "x": -715.855,
          "z": 546.615
        },
        {
          "x": -715.883,
          "z": 550.299
        },
        {
          "x": -711.628,
          "z": 550.333
        }
      ],
      "height_m": 3.5,
      "id": "way/411124180",
      "levels": 0,
      "name": null
    },
    {
      "building": "house",
      "footprint": [
        {
          "x": -605.094,
          "z": 564.904
        },
        {
          "x": -611.805,
          "z": 564.882
        },
        {
          "x": -611.832,
          "z": 572.764
        },
        {
          "x": -605.122,
          "z": 572.786
        },
        {
          "x": -605.094,
          "z": 564.904
        }
      ],
      "height_m": 4.6,
      "id": "way/411124188",
      "levels": 0,
      "name": null
    },
    {
      "building": "residential",
      "footprint": [
        {
          "x": -606.257,
          "z": 625.841
        },
        {
          "x": -612.903,
          "z": 625.808
        },
        {
          "x": -612.931,
          "z": 631.151
        },
        {
          "x": -606.285,
          "z": 631.196
        },
        {
          "x": -606.257,
          "z": 625.841
        }
      ],
      "height_m": 3.4,
      "id": "way/411124200",
      "levels": 0,
      "name": null
    },
    {
      "building": "residential",
      "footprint": [
        {
          "x": -606.903,
          "z": 653.493
        },
        {
          "x": -606.793,
          "z": 647.348
        },
        {
          "x": -612.875,
          "z": 647.237
        },
        {
          "x": -612.986,
          "z": 653.382
        },
        {
          "x": -606.903,
          "z": 653.493
        }
      ],
      "height_m": 3.8,
      "id": "way/411124202",
      "levels": 0,
      "name": null
    },
    {
      "building": "house",
      "footprint": [
        {
          "x": -614.731,
          "z": 631.452
        },
        {
          "x": -614.749,
          "z": 626.064
        },
        {
          "x": -620.112,
          "z": 626.086
        },
        {
          "x": -620.093,
          "z": 631.474
        },
        {
          "x": -614.731,
          "z": 631.452
        }
      ],
      "height_m": 3.6,
      "id": "way/411124203",
      "levels": 0,
      "name": null
    },
    {
      "building": "residential",
      "footprint": [
        {
          "x": -715.661,
          "z": 631.507
        },
        {
          "x": -709.634,
          "z": 631.452
        },
        {
          "x": -709.717,
          "z": 623.036
        },
        {
          "x": -715.735,
          "z": 623.091
        },
        {
          "x": -715.661,
          "z": 631.507
        }
      ],
      "height_m": 3.6,
      "id": "way/411124208",
      "levels": 0,
      "name": null
    },
    {
      "building": "apartments",
      "footprint": [
        {
          "x": -622.585,
          "z": 678.384
        },
        {
          "x": -622.595,
          "z": 684.095
        },
        {
          "x": -613.281,
          "z": 684.117
        },
        {
          "x": -613.263,
          "z": 678.406
        },
        {
          "x": -622.585,
          "z": 678.384
        }
      ],
      "height_m": 3.5,
      "id": "way/411124210",
      "levels": 0,
      "name": null
    },
    {
      "building": "house",
      "footprint": [
        {
          "x": -613.964,
          "z": 600.705
        },
        {
          "x": -614.057,
          "z": 595.273
        },
        {
          "x": -619.89,
          "z": 595.373
        },
        {
          "x": -619.807,
          "z": 600.794
        },
        {
          "x": -613.964,
          "z": 600.705
        }
      ],
      "height_m": 3.8,
      "id": "way/411124217",
      "levels": 0,
      "name": null
    },
    {
      "building": "house",
      "footprint": [
        {
          "x": -605.334,
          "z": 587.057
        },
        {
          "x": -605.408,
          "z": 580.311
        },
        {
          "x": -611.602,
          "z": 580.389
        },
        {
          "x": -611.518,
          "z": 587.135
        },
        {
          "x": -605.334,
          "z": 587.057
        }
      ],
      "height_m": 3.9,
      "id": "way/411124223",
      "levels": 0,
      "name": null
    },
    {
      "building": "house",
      "footprint": [
        {
          "x": -711.323,
          "z": 683.861
        },
        {
          "x": -716.953,
          "z": 683.894
        },
        {
          "x": -716.898,
          "z": 692.644
        },
        {
          "x": -711.277,
          "z": 692.611
        },
        {
          "x": -711.323,
          "z": 683.861
        }
      ],
      "height_m": 3.4,
      "id": "way/411124229",
      "levels": 0,
      "name": null
    },
    {
      "building": "house",
      "footprint": [
        {
          "x": -709.643,
          "z": 613.551
        },
        {
          "x": -709.569,
          "z": 608.019
        },
        {
          "x": -715.79,
          "z": 607.93
        },
        {
          "x": -715.864,
          "z": 613.462
        },
        {
          "x": -709.643,
          "z": 613.551
        }
      ],
      "height_m": 6.5,
      "id": "way/411124235",
      "levels": 0,
      "name": null
    },
    {
      "building": "house",
      "footprint": [
        {
          "x": -717.71,
          "z": 653.782
        },
        {
          "x": -717.803,
          "z": 661.742
        },
        {
          "x": -714.572,
          "z": 661.786
        },
        {
          "x": -714.544,
          "z": 659.248
        },
        {
          "x": -711.443,
          "z": 659.282
        },
        {
          "x": -711.388,
          "z": 653.849
        },
        {
          "x": -717.71,
          "z": 653.782
        }
      ],
      "height_m": 4.0,
      "id": "way/411124254",
      "levels": 0,
      "name": null
    },
    {
      "building": "house",
      "footprint": [
        {
          "x": -709.043,
          "z": 613.106
        },
        {
          "x": -699.97,
          "z": 613.062
        },
        {
          "x": -699.998,
          "z": 607.74
        },
        {
          "x": -705.305,
          "z": 607.774
        },
        {
          "x": -705.305,
          "z": 607.518
        },
        {
          "x": -709.08,
          "z": 607.54
        },
        {
          "x": -709.043,
          "z": 613.106
        }
      ],
      "height_m": 3.6,
      "id": "way/411124255",
      "levels": 0,
      "name": null
    },
    {
      "building": "house",
      "footprint": [
        {
          "x": -708.766,
          "z": 709.977
        },
        {
          "x": -699.998,
          "z": 710.133
        },
        {
          "x": -699.887,
          "z": 699.446
        },
        {
          "x": -702.453,
          "z": 699.446
        },
        {
          "x": -702.453,
          "z": 699.847
        },
        {
          "x": -708.591,
          "z": 699.869
        },
        {
          "x": -708.766,
          "z": 709.977
        }
      ],
      "height_m": 5.4,
      "id": "way/411124257",
      "levels": 0,
      "name": null
    },
    {
      "building": "house",
      "footprint": [
        {
          "x": -696.232,
          "z": 688.113
        },
        {
          "x": -696.213,
          "z": 685.72
        },
        {
          "x": -696.5,
          "z": 685.72
        },
        {
          "x": -696.49,
          "z": 684.395
        },
        {
          "x": -708.074,
          "z": 684.306
        },
        {
          "x": -708.102,
          "z": 688.024
        },
        {
          "x": -696.232,
          "z": 688.113
        }
      ],
      "height_m": 3.9,
      "id": "way/411124265",
      "levels": 0,
      "name": null
    },
    {
      "building": "house",
      "footprint": [
        {
          "x": -625.419,
          "z": 564.493
        },
        {
          "x": -625.382,
          "z": 554.14
        },
        {
          "x": -631.105,
          "z": 554.14
        },
        {
          "x": -631.077,
          "z": 551.802
        },
        {
          "x": -643.344,
          "z": 551.758
        },
        {
          "x": -643.39,
          "z": 564.437
        },
        {
          "x": -625.419,
          "z": 564.493
        }
      ],
      "height_m": 5.7,
      "id": "way/411124269",
      "levels": 0,
      "name": null
    },
    {
      "building": "house",
      "footprint": [
        {
          "x": -613.088,
          "z": 616.19
        },
        {
          "x": -612.977,
          "z": 610.579
        },
        {
          "x": -619.918,
          "z": 610.445
        },
        {
          "x": -619.936,
          "z": 610.924
        },
        {
          "x": -620.878,
          "z": 610.902
        },
        {
          "x": -620.979,
          "z": 616.045
        },
        {
          "x": -613.088,
          "z": 616.19
        }
      ],
      "height_m": 3.4,
      "id": "way/411124275",
      "levels": 0,
      "name": null
    },
    {
      "building": "house",
      "footprint": [
        {
          "x": -700.598,
          "z": 623.292
        },
        {
          "x": -706.523,
          "z": 623.214
        },
        {
          "x": -706.523,
          "z": 623.615
        },
        {
          "x": -707.64,
          "z": 623.604
        },
        {
          "x": -707.733,
          "z": 629.96
        },
        {
          "x": -700.69,
          "z": 630.06
        },
        {
          "x": -700.598,
          "z": 623.292
        }
      ],
      "height_m": 4.8,
      "id": "way/411124276",
      "levels": 0,
      "name": null
    },
    {
      "building": "house",
      "footprint": [
        {
          "x": -702.296,
          "z": 598.056
        },
        {
          "x": -702.231,
          "z": 592.49
        },
        {
          "x": -707.788,
          "z": 592.423
        },
        {
          "x": -707.797,
          "z": 592.857
        },
        {
          "x": -708.416,
          "z": 592.846
        },
        {
          "x": -708.443,
          "z": 595.384
        },
        {
          "x": -707.825,
          "z": 595.384
        },
        {
          "x": -707.853,
          "z": 598.0
        },
        {
          "x": -702.296,
          "z": 598.056
        }
      ],
      "height_m": 3.2,
      "id": "way/411124284",
      "levels": 0,
      "name": null
    },
    {
      "building": "residential",
      "footprint": [
        {
          "x": -706.182,
          "z": 546.548
        },
        {
          "x": -708.96,
          "z": 546.514
        },
        {
          "x": -709.052,
          "z": 554.418
        },
        {
          "x": -708.129,
          "z": 554.429
        },
        {
          "x": -708.111,
          "z": 552.682
        },
        {
          "x": -707.197,
          "z": 552.693
        },
        {
          "x": -707.169,
          "z": 549.776
        },
        {
          "x": -706.219,
          "z": 549.787
        },
        {
          "x": -706.182,
          "z": 546.548
        }
      ],
      "height_m": 3.3,
      "id": "way/411124289",
      "levels": 0,
      "name": null
    },
    {
      "building": "house",
      "footprint": [
        {
          "x": -613.281,
          "z": 558.782
        },
        {
          "x": -613.235,
          "z": 555.064
        },
        {
          "x": -612.931,
          "z": 555.075
        },
        {
          "x": -612.848,
          "z": 549.598
        },
        {
          "x": -620.398,
          "z": 549.498
        },
        {
          "x": -620.472,
          "z": 555.108
        },
        {
          "x": -620.01,
          "z": 555.119
        },
        {
          "x": -620.066,
          "z": 558.682
        },
        {
          "x": -613.281,
          "z": 558.782
        }
      ],
      "height_m": 3.7,
      "id": "way/411124312",
      "levels": 0,
      "name": null
    },
    {
      "building": "house",
      "footprint": [
        {
          "x": -626.923,
          "z": 624.995
        },
        {
          "x": -626.813,
          "z": 617.336
        },
        {
          "x": -627.413,
          "z": 617.325
        },
        {
          "x": -627.357,
          "z": 613.34
        },
        {
          "x": -636.8,
          "z": 613.217
        },
        {
          "x": -636.855,
          "z": 617.481
        },
        {
          "x": -643.251,
          "z": 617.392
        },
        {
          "x": -643.353,
          "z": 624.761
        },
        {
          "x": -626.923,
          "z": 624.995
        }
      ],
      "height_m": 8.8,
      "id": "way/411124316",
      "levels": 0,
      "name": null
    }
  ],
  "coord_x": -4,
  "coord_z": 3,
  "counts": {
    "areas": 0,
    "buildings": 84,
    "junctions": 2,
    "pois": 0,
    "streets": 3
  },
  "id": "-4_3",
  "junctions": [
    {
      "connected_road_count": 2,
      "highways": [
        "residential"
      ],
      "id": "123451117",
      "position": {
        "x": -565.054,
        "z": 668.376
      },
      "radius_m": 3.684
    },
    {
      "connected_road_count": 2,
      "highways": [
        "residential"
      ],
      "id": "123665087",
      "position": {
        "x": -659.755,
        "z": 667.998
      },
      "radius_m": 3.684
    }
  ],
  "pois": [],
  "schema": "gangland.unity_city_chunk.v1",
  "streets": [
    {
      "centerline": [
        {
          "x": -659.755,
          "z": 667.998
        },
        {
          "x": -660.613,
          "z": 511.393
        }
      ],
      "crossing": null,
      "end_node_id": "2995090749",
      "estimated_road_width_m": 6.8,
      "highway": "residential",
      "id": "way/13448145#section/1",
      "lane_count": 2,
      "lane_source": "inferred",
      "lane_width_m": 3.4,
      "maxspeed": null,
      "name": "South Mullen Avenue",
      "oneway": false,
      "parent_id": "way/13448145",
      "render_kind": "road",
      "road_width_m": 6.8,
      "section_index": 1,
      "start_node_id": "123665087",
      "surface": "asphalt",
      "trim_end_m": 0,
      "trim_start_m": 0,
      "turn_lanes": null
    },
    {
      "centerline": [
        {
          "x": -565.054,
          "z": 668.376
        },
        {
          "x": -659.755,
          "z": 667.998
        }
      ],
      "crossing": null,
      "end_node_id": "123665087",
      "estimated_road_width_m": 6.8,
      "highway": "residential",
      "id": "way/509313137#section/7",
      "lane_count": 2,
      "lane_source": "osm",
      "lane_width_m": 3.4,
      "maxspeed": null,
      "name": "West 52nd Street",
      "oneway": false,
      "parent_id": "way/509313137",
      "render_kind": "road",
      "road_width_m": 6.8,
      "section_index": 7,
      "start_node_id": "123451117",
      "surface": "asphalt",
      "trim_end_m": 0,
      "trim_start_m": 0,
      "turn_lanes": null
    },
    {
      "centerline": [
        {
          "x": -565.054,
          "z": 668.376
        },
        {
          "x": -564.916,
          "z": 512.005
        }
      ],
      "crossing": null,
      "end_node_id": "2995090779",
      "estimated_road_width_m": 6.8,
      "highway": "residential",
      "id": "way/1347434461#section/1",
      "lane_count": 2,
      "lane_source": "inferred",
      "lane_width_m": 3.4,
      "maxspeed": null,
      "name": "Deane Avenue",
      "oneway": false,
      "parent_id": "way/1347434461",
      "render_kind": "road",
      "road_width_m": 6.8,
      "section_index": 1,
      "start_node_id": "123451117",
      "surface": "asphalt",
      "trim_end_m": 0,
      "trim_start_m": 0,
      "turn_lanes": null
    }
  ],
  "terrain": {
    "columns": 2,
    "origin_elevation_m": 58.0,
    "points": [
      {
        "elevation_m": 82.0,
        "relative_y_m": 24.0,
        "x": -720.0,
        "z": 540.0
      },
      {
        "elevation_m": 78.0,
        "relative_y_m": 20.0,
        "x": -540.0,
        "z": 540.0
      },
      {
        "elevation_m": 84.0,
        "relative_y_m": 26.0,
        "x": -720.0,
        "z": 720.0
      },
      {
        "elevation_m": 83.0,
        "relative_y_m": 25.0,
        "x": -540.0,
        "z": 720.0
      }
    ],
    "rows": 2,
    "schema": "gangland.unity_city_terrain.v1",
    "source": "Open-Meteo Elevation API, Copernicus DEM GLO-90",
    "spacing_m": 180
  }
}
