{
  "areas": [
    {
      "amenity": "school",
      "footprint": [
        {
          "x": -237.914,
          "z": -81.62
        },
        {
          "x": -314.126,
          "z": -82.076
        },
        {
          "x": -315.206,
          "z": -40.465
        },
        {
          "x": -238.274,
          "z": -40.543
        },
        {
          "x": -237.914,
          "z": -81.62
        }
      ],
      "id": "way/1168772995",
      "landuse": "religious",
      "leisure": null,
      "name": null,
      "shop": null
    }
  ],
  "bounds": {
    "max_x": -180,
    "max_z": 0,
    "min_x": -360,
    "min_z": -180
  },
  "buildings": [
    {
      "building": "residential",
      "footprint": [
        {
          "x": -226.93,
          "z": -30.735
        },
        {
          "x": -220.967,
          "z": -30.691
        },
        {
          "x": -220.921,
          "z": -36.569
        },
        {
          "x": -221.429,
          "z": -36.58
        },
        {
          "x": -221.42,
          "z": -37.604
        },
        {
          "x": -222.832,
          "z": -37.615
        },
        {
          "x": -222.813,
          "z": -39.574
        },
        {
          "x": -226.469,
          "z": -39.597
        },
        {
          "x": -226.496,
          "z": -36.613
        },
        {
          "x": -226.884,
          "z": -36.624
        },
        {
          "x": -226.93,
          "z": -30.735
        }
      ],
      "height_m": 4.8,
      "id": "way/407024323",
      "levels": 0,
      "name": null
    },
    {
      "building": "house",
      "footprint": [
        {
          "x": -194.819,
          "z": -72.057
        },
        {
          "x": -200.043,
          "z": -72.035
        },
        {
          "x": -200.034,
          "z": -70.221
        },
        {
          "x": -203.449,
          "z": -70.21
        },
        {
          "x": -203.393,
          "z": -57.708
        },
        {
          "x": -204.178,
          "z": -57.708
        },
        {
          "x": -204.159,
          "z": -54.447
        },
        {
          "x": -195.142,
          "z": -54.491
        },
        {
          "x": -195.142,
          "z": -56.061
        },
        {
          "x": -194.745,
          "z": -56.061
        },
        {
          "x": -194.819,
          "z": -72.057
        }
      ],
      "height_m": 5.9,
      "id": "way/407024325",
      "levels": 0,
      "name": null
    },
    {
      "building": "house",
      "footprint": [
        {
          "x": -265.853,
          "z": -109.416
        },
        {
          "x": -260.02,
          "z": -109.45
        },
        {
          "x": -260.029,
          "z": -110.786
        },
        {
          "x": -255.691,
          "z": -110.797
        },
        {
          "x": -255.7,
          "z": -115.06
        },
        {
          "x": -254.546,
          "z": -115.06
        },
        {
          "x": -254.565,
          "z": -122.697
        },
        {
          "x": -259.051,
          "z": -122.686
        },
        {
          "x": -259.051,
          "z": -121.461
        },
        {
          "x": -265.909,
          "z": -121.472
        },
        {
          "x": -265.853,
          "z": -109.416
        }
      ],
      "height_m": 6.4,
      "id": "way/407024331",
      "levels": 0,
      "name": null
    },
    {
      "building": "house",
      "footprint": [
        {
          "x": -275.535,
          "z": -181.173
        },
        {
          "x": -284.664,
          "z": -181.273
        },
        {
          "x": -284.673,
          "z": -180.505
        },
        {
          "x": -287.774,
          "z": -180.539
        },
        {
          "x": -287.968,
          "z": -164.909
        },
        {
          "x": -280.003,
          "z": -164.776
        },
        {
          "x": -279.957,
          "z": -168.004
        },
        {
          "x": -276.218,
          "z": -167.96
        },
        {
          "x": -276.218,
          "z": -168.449
        },
        {
          "x": -275.665,
          "z": -168.449
        },
        {
          "x": -275.535,
          "z": -181.173
        }
      ],
      "height_m": 5.3,
      "id": "way/407024332",
      "levels": 0,
      "name": null
    },
    {
      "building": "retail",
      "footprint": [
        {
          "x": -218.318,
          "z": -31.036
        },
        {
          "x": -218.208,
          "z": -36.613
        },
        {
          "x": -217.469,
          "z": -36.602
        },
        {
          "x": -217.497,
          "z": -35.121
        },
        {
          "x": -213.833,
          "z": -35.055
        },
        {
          "x": -213.805,
          "z": -36.524
        },
        {
          "x": -211.848,
          "z": -36.491
        },
        {
          "x": -211.793,
          "z": -39.096
        },
        {
          "x": -220.044,
          "z": -39.207
        },
        {
          "x": -219.998,
          "z": -31.114
        },
        {
          "x": -218.318,
          "z": -31.036
        }
      ],
      "height_m": 3.1,
      "id": "way/407024341",
      "levels": 0,
      "name": null
    },
    {
      "building": "house",
      "footprint": [
        {
          "x": -240.637,
          "z": -171.433
        },
        {
          "x": -242.344,
          "z": -171.411
        },
        {
          "x": -242.372,
          "z": -173.114
        },
        {
          "x": -247.495,
          "z": -173.047
        },
        {
          "x": -247.476,
          "z": -171.522
        },
        {
          "x": -249.479,
          "z": -171.5
        },
        {
          "x": -249.267,
          "z": -157.039
        },
        {
          "x": -244.412,
          "z": -157.117
        },
        {
          "x": -244.43,
          "z": -158.475
        },
        {
          "x": -240.443,
          "z": -158.531
        },
        {
          "x": -240.637,
          "z": -171.433
        }
      ],
      "height_m": 4.2,
      "id": "way/407024343",
      "levels": 0,
      "name": null
    },
    {
      "building": "residential",
      "footprint": [
        {
          "x": -205.027,
          "z": -160.345
        },
        {
          "x": -193.591,
          "z": -160.201
        },
        {
          "x": -193.499,
          "z": -167.704
        },
        {
          "x": -193.545,
          "z": -168.772
        },
        {
          "x": -193.969,
          "z": -169.518
        },
        {
          "x": -195.4,
          "z": -169.752
        },
        {
          "x": -195.409,
          "z": -170.464
        },
        {
          "x": -196.037,
          "z": -171.166
        },
        {
          "x": -203.956,
          "z": -171.344
        },
        {
          "x": -204.658,
          "z": -170.921
        },
        {
          "x": -204.898,
          "z": -170.253
        },
        {
          "x": -205.027,
          "z": -160.345
        }
      ],
      "height_m": 6.9,
      "id": "way/407024351",
      "levels": 0,
      "name": null
    },
    {
      "building": "house",
      "footprint": [
        {
          "x": -210.242,
          "z": -124.389
        },
        {
          "x": -210.362,
          "z": -124.389
        },
        {
          "x": -210.344,
          "z": -128.274
        },
        {
          "x": -216.482,
          "z": -128.296
        },
        {
          "x": -216.491,
          "z": -127.35
        },
        {
          "x": -218.817,
          "z": -127.361
        },
        {
          "x": -218.9,
          "z": -110.118
        },
        {
          "x": -217.257,
          "z": -110.107
        },
        {
          "x": -217.266,
          "z": -108.37
        },
        {
          "x": -211.857,
          "z": -108.337
        },
        {
          "x": -211.848,
          "z": -110.151
        },
        {
          "x": -210.307,
          "z": -110.14
        },
        {
          "x": -210.242,
          "z": -124.389
        }
      ],
      "height_m": 6.6,
      "id": "way/407024357",
      "levels": 0,
      "name": null
    },
    {
      "building": "house",
      "footprint": [
        {
          "x": -254.076,
          "z": -170.253
        },
        {
          "x": -257.371,
          "z": -170.297
        },
        {
          "x": -257.361,
          "z": -171.288
        },
        {
          "x": -263.213,
          "z": -171.377
        },
        {
          "x": -263.324,
          "z": -164.075
        },
        {
          "x": -264.607,
          "z": -164.097
        },
        {
          "x": -264.672,
          "z": -159.789
        },
        {
          "x": -259.974,
          "z": -159.711
        },
        {
          "x": -259.983,
          "z": -159.021
        },
        {
          "x": -258.432,
          "z": -158.998
        },
        {
          "x": -258.423,
          "z": -159.677
        },
        {
          "x": -254.232,
          "z": -159.611
        },
        {
          "x": -254.076,
          "z": -170.253
        }
      ],
      "height_m": 4.9,
      "id": "way/407024370",
      "levels": 0,
      "name": null
    },
    {
      "building": "residential",
      "footprint": [
        {
          "x": -234.803,
          "z": -8.048
        },
        {
          "x": -235.043,
          "z": -8.004
        },
        {
          "x": -235.062,
          "z": -4.152
        },
        {
          "x": -229.791,
          "z": -4.085
        },
        {
          "x": -229.754,
          "z": -7.57
        },
        {
          "x": -224.475,
          "z": -7.547
        },
        {
          "x": -224.447,
          "z": -14.817
        },
        {
          "x": -223.256,
          "z": -14.806
        },
        {
          "x": -223.22,
          "z": -23.544
        },
        {
          "x": -228.97,
          "z": -23.555
        },
        {
          "x": -228.951,
          "z": -25.771
        },
        {
          "x": -234.739,
          "z": -25.793
        },
        {
          "x": -234.803,
          "z": -8.048
        }
      ],
      "height_m": 7.5,
      "id": "way/407024373",
      "levels": 0,
      "name": null
    },
    {
      "building": "residential",
      "footprint": [
        {
          "x": -241.79,
          "z": -130.267
        },
        {
          "x": -250.005,
          "z": -130.2
        },
        {
          "x": -249.941,
          "z": -122.775
        },
        {
          "x": -249.276,
          "z": -122.775
        },
        {
          "x": -249.174,
          "z": -110.507
        },
        {
          "x": -245.833,
          "z": -110.53
        },
        {
          "x": -245.815,
          "z": -108.559
        },
        {
          "x": -240.637,
          "z": -108.604
        },
        {
          "x": -240.775,
          "z": -124.723
        },
        {
          "x": -241.061,
          "z": -124.723
        },
        {
          "x": -241.07,
          "z": -125.402
        },
        {
          "x": -241.763,
          "z": -127.294
        },
        {
          "x": -241.79,
          "z": -130.267
        }
      ],
      "height_m": 5.6,
      "id": "way/407024374",
      "levels": 0,
      "name": null
    },
    {
      "building": "apartments",
      "footprint": [
        {
          "x": -266.167,
          "z": -4.442
        },
        {
          "x": -266.158,
          "z": -10.408
        },
        {
          "x": -267.395,
          "z": -10.42
        },
        {
          "x": -267.339,
          "z": -14.806
        },
        {
          "x": -270.773,
          "z": -14.85
        },
        {
          "x": -270.736,
          "z": -17.622
        },
        {
          "x": -275.203,
          "z": -17.689
        },
        {
          "x": -275.24,
          "z": -14.694
        },
        {
          "x": -274.354,
          "z": -14.694
        },
        {
          "x": -274.391,
          "z": -11.444
        },
        {
          "x": -275.425,
          "z": -11.455
        },
        {
          "x": -275.554,
          "z": -4.475
        },
        {
          "x": -266.167,
          "z": -4.442
        }
      ],
      "height_m": 9.4,
      "id": "way/407024376",
      "levels": 0,
      "name": null
    },
    {
      "building": "house",
      "footprint": [
        {
          "x": -195.04,
          "z": -118.634
        },
        {
          "x": -193.397,
          "z": -118.634
        },
        {
          "x": -193.416,
          "z": -121.74
        },
        {
          "x": -195.003,
          "z": -121.74
        },
        {
          "x": -195.022,
          "z": -125.647
        },
        {
          "x": -195.271,
          "z": -125.647
        },
        {
          "x": -195.289,
          "z": -127.751
        },
        {
          "x": -197.818,
          "z": -127.74
        },
        {
          "x": -197.828,
          "z": -128.998
        },
        {
          "x": -204.529,
          "z": -128.964
        },
        {
          "x": -204.51,
          "z": -125.113
        },
        {
          "x": -203.67,
          "z": -125.113
        },
        {
          "x": -203.569,
          "z": -108.214
        },
        {
          "x": -194.985,
          "z": -108.27
        },
        {
          "x": -195.04,
          "z": -118.634
        }
      ],
      "height_m": 6.2,
      "id": "way/407024386",
      "levels": 0,
      "name": null
    },
    {
      "building": "commercial",
      "footprint": [
        {
          "x": -301.786,
          "z": -16.075
        },
        {
          "x": -301.786,
          "z": -16.386
        },
        {
          "x": -299.266,
          "z": -16.364
        },
        {
          "x": -299.275,
          "z": -16.052
        },
        {
          "x": -293.174,
          "z": -15.986
        },
        {
          "x": -293.109,
          "z": -22.041
        },
        {
          "x": -294.457,
          "z": -22.052
        },
        {
          "x": -294.439,
          "z": -23.8
        },
        {
          "x": -299.921,
          "z": -23.867
        },
        {
          "x": -299.903,
          "z": -25.403
        },
        {
          "x": -306.004,
          "z": -25.47
        },
        {
          "x": -306.013,
          "z": -23.934
        },
        {
          "x": -307.73,
          "z": -23.945
        },
        {
          "x": -307.813,
          "z": -16.141
        },
        {
          "x": -301.786,
          "z": -16.075
        }
      ],
      "height_m": 7.1,
      "id": "way/407024387",
      "levels": 0,
      "name": null
    },
    {
      "building": "retail",
      "footprint": [
        {
          "x": -214.303,
          "z": -24.323
        },
        {
          "x": -214.303,
          "z": -24.858
        },
        {
          "x": -217.183,
          "z": -24.835
        },
        {
          "x": -217.183,
          "z": -24.301
        },
        {
          "x": -219.98,
          "z": -24.29
        },
        {
          "x": -219.841,
          "z": -8.65
        },
        {
          "x": -216.602,
          "z": -8.683
        },
        {
          "x": -216.592,
          "z": -6.902
        },
        {
          "x": -207.658,
          "z": -6.969
        },
        {
          "x": -207.704,
          "z": -13.915
        },
        {
          "x": -208.461,
          "z": -13.904
        },
        {
          "x": -208.488,
          "z": -17.8
        },
        {
          "x": -207.722,
          "z": -17.811
        },
        {
          "x": -207.768,
          "z": -24.379
        },
        {
          "x": -214.303,
          "z": -24.323
        }
      ],
      "height_m": 7.3,
      "id": "way/407024391",
      "levels": 0,
      "name": null
    },
    {
      "building": "yes",
      "footprint": [
        {
          "x": -204.159,
          "z": -9.351
        },
        {
          "x": -203.735,
          "z": -9.362
        },
        {
          "x": -203.698,
          "z": -3.863
        },
        {
          "x": -196.009,
          "z": -3.874
        },
        {
          "x": -195.917,
          "z": -7.169
        },
        {
          "x": -194.376,
          "z": -7.18
        },
        {
          "x": -194.403,
          "z": -12.39
        },
        {
          "x": -193.12,
          "z": -12.39
        },
        {
          "x": -193.185,
          "z": -21.886
        },
        {
          "x": -194.413,
          "z": -21.874
        },
        {
          "x": -194.422,
          "z": -22.709
        },
        {
          "x": -195.705,
          "z": -22.709
        },
        {
          "x": -195.723,
          "z": -24.568
        },
        {
          "x": -204.261,
          "z": -24.513
        },
        {
          "x": -204.159,
          "z": -9.351
        }
      ],
      "height_m": 6.2,
      "id": "way/407024398",
      "levels": 0,
      "name": "Crenshaw Caregivers"
    },
    {
      "building": "house",
      "footprint": [
        {
          "x": -179.137,
          "z": -172.479
        },
        {
          "x": -187.047,
          "z": -172.524
        },
        {
          "x": -187.112,
          "z": -161.18
        },
        {
          "x": -189.105,
          "z": -161.191
        },
        {
          "x": -189.161,
          "z": -152.575
        },
        {
          "x": -182.986,
          "z": -152.542
        },
        {
          "x": -182.977,
          "z": -154.189
        },
        {
          "x": -182.423,
          "z": -154.189
        },
        {
          "x": -182.413,
          "z": -155.436
        },
        {
          "x": -183.078,
          "z": -155.447
        },
        {
          "x": -183.05,
          "z": -160.501
        },
        {
          "x": -181.97,
          "z": -160.49
        },
        {
          "x": -181.98,
          "z": -158.887
        },
        {
          "x": -179.211,
          "z": -158.876
        },
        {
          "x": -179.137,
          "z": -172.479
        }
      ],
      "height_m": 5.6,
      "id": "way/407024400",
      "levels": 0,
      "name": null
    },
    {
      "building": "house",
      "footprint": [
        {
          "x": -219.057,
          "z": -152.508
        },
        {
          "x": -214.433,
          "z": -152.475
        },
        {
          "x": -214.423,
          "z": -153.176
        },
        {
          "x": -212.605,
          "z": -153.165
        },
        {
          "x": -212.587,
          "z": -154.891
        },
        {
          "x": -210.842,
          "z": -154.868
        },
        {
          "x": -210.722,
          "z": -171.121
        },
        {
          "x": -213.223,
          "z": -171.143
        },
        {
          "x": -213.205,
          "z": -172.98
        },
        {
          "x": -216.565,
          "z": -173.014
        },
        {
          "x": -216.574,
          "z": -171.221
        },
        {
          "x": -219.094,
          "z": -171.232
        },
        {
          "x": -219.168,
          "z": -161.002
        },
        {
          "x": -218.992,
          "z": -160.991
        },
        {
          "x": -219.02,
          "z": -157.028
        },
        {
          "x": -219.057,
          "z": -152.508
        }
      ],
      "height_m": 8.8,
      "id": "way/407024402",
      "levels": 0,
      "name": null
    },
    {
      "building": "apartments",
      "footprint": [
        {
          "x": -339.703,
          "z": -130.979
        },
        {
          "x": -339.694,
          "z": -131.87
        },
        {
          "x": -341.77,
          "z": -131.881
        },
        {
          "x": -341.77,
          "z": -131.035
        },
        {
          "x": -353.299,
          "z": -131.102
        },
        {
          "x": -353.289,
          "z": -131.847
        },
        {
          "x": -355.458,
          "z": -131.859
        },
        {
          "x": -355.458,
          "z": -131.09
        },
        {
          "x": -360.895,
          "z": -131.124
        },
        {
          "x": -360.923,
          "z": -127.907
        },
        {
          "x": -360.507,
          "z": -127.896
        },
        {
          "x": -360.526,
          "z": -124.122
        },
        {
          "x": -359.317,
          "z": -124.122
        },
        {
          "x": -359.335,
          "z": -120.025
        },
        {
          "x": -344.964,
          "z": -119.936
        },
        {
          "x": -344.955,
          "z": -122.14
        },
        {
          "x": -337.137,
          "z": -122.096
        },
        {
          "x": -337.081,
          "z": -130.968
        },
        {
          "x": -339.703,
          "z": -130.979
        }
      ],
      "height_m": 5.2,
      "id": "way/407024436",
      "levels": 0,
      "name": null
    },
    {
      "building": "house",
      "footprint": [
        {
          "x": -231.13,
          "z": -171.366
        },
        {
          "x": -231.647,
          "z": -171.366
        },
        {
          "x": -231.647,
          "z": -171.689
        },
        {
          "x": -234.213,
          "z": -171.733
        },
        {
          "x": -234.213,
          "z": -171.422
        },
        {
          "x": -235.237,
          "z": -171.433
        },
        {
          "x": -235.375,
          "z": -163.306
        },
        {
          "x": -233.373,
          "z": -163.273
        },
        {
          "x": -233.391,
          "z": -162.082
        },
        {
          "x": -229.616,
          "z": -162.015
        },
        {
          "x": -229.662,
          "z": -159.121
        },
        {
          "x": -224.013,
          "z": -159.021
        },
        {
          "x": -223.949,
          "z": -162.906
        },
        {
          "x": -223.441,
          "z": -162.895
        },
        {
          "x": -223.303,
          "z": -171.232
        },
        {
          "x": -224.641,
          "z": -171.255
        },
        {
          "x": -224.632,
          "z": -171.689
        },
        {
          "x": -227.115,
          "z": -171.733
        },
        {
          "x": -227.124,
          "z": -171.299
        },
        {
          "x": -227.631,
          "z": -171.31
        },
        {
          "x": -227.604,
          "z": -172.513
        },
        {
          "x": -231.111,
          "z": -172.568
        },
        {
          "x": -231.13,
          "z": -171.366
        }
      ],
      "height_m": 8.8,
      "id": "way/407024492",
      "levels": 0,
      "name": null
    },
    {
      "building": "retail",
      "footprint": [
        {
          "x": -250.282,
          "z": -3.161
        },
        {
          "x": -238.117,
          "z": -3.117
        },
        {
          "x": -238.117,
          "z": -5.143
        },
        {
          "x": -238.689,
          "z": -5.143
        },
        {
          "x": -238.689,
          "z": -9.184
        },
        {
          "x": -239.446,
          "z": -9.184
        },
        {
          "x": -239.437,
          "z": -10.542
        },
        {
          "x": -238.846,
          "z": -10.542
        },
        {
          "x": -238.855,
          "z": -21.218
        },
        {
          "x": -239.308,
          "z": -21.218
        },
        {
          "x": -239.308,
          "z": -21.685
        },
        {
          "x": -240.821,
          "z": -21.685
        },
        {
          "x": -240.821,
          "z": -22.442
        },
        {
          "x": -242.575,
          "z": -22.442
        },
        {
          "x": -242.575,
          "z": -21.685
        },
        {
          "x": -248.39,
          "z": -21.685
        },
        {
          "x": -248.39,
          "z": -20.828
        },
        {
          "x": -249.304,
          "z": -20.828
        },
        {
          "x": -249.313,
          "z": -17.811
        },
        {
          "x": -249.83,
          "z": -17.811
        },
        {
          "x": -249.83,
          "z": -10.086
        },
        {
          "x": -248.584,
          "z": -10.086
        },
        {
          "x": -248.584,
          "z": -9.151
        },
        {
          "x": -250.356,
          "z": -9.106
        },
        {
          "x": -250.291,
          "z": -4.13
        },
        {
          "x": -250.282,
          "z": -3.161
        }
      ],
      "height_m": 7.1,
      "id": "way/407024524",
      "levels": 0,
      "name": null
    },
    {
      "building": "yes",
      "footprint": [
        {
          "x": -260.509,
          "z": -51.708
        },
        {
          "x": -260.454,
          "z": -59.901
        },
        {
          "x": -266.472,
          "z": -59.935
        },
        {
          "x": -266.398,
          "z": -72.091
        },
        {
          "x": -262.133,
          "z": -72.069
        },
        {
          "x": -262.078,
          "z": -79.727
        },
        {
          "x": -264.755,
          "z": -79.739
        },
        {
          "x": -264.746,
          "z": -80.061
        },
        {
          "x": -286.473,
          "z": -80.195
        },
        {
          "x": -286.482,
          "z": -78.681
        },
        {
          "x": -294.023,
          "z": -78.726
        },
        {
          "x": -294.023,
          "z": -79.438
        },
        {
          "x": -295.786,
          "z": -79.449
        },
        {
          "x": -295.795,
          "z": -78.737
        },
        {
          "x": -305.57,
          "z": -78.803
        },
        {
          "x": -305.579,
          "z": -77.512
        },
        {
          "x": -310.407,
          "z": -77.546
        },
        {
          "x": -310.425,
          "z": -74.05
        },
        {
          "x": -309.964,
          "z": -74.039
        },
        {
          "x": -309.973,
          "z": -72.993
        },
        {
          "x": -309.114,
          "z": -72.993
        },
        {
          "x": -309.179,
          "z": -62.896
        },
        {
          "x": -307.536,
          "z": -62.885
        },
        {
          "x": -307.545,
          "z": -61.682
        },
        {
          "x": -293.433,
          "z": -61.593
        },
        {
          "x": -293.433,
          "z": -61.304
        },
        {
          "x": -285.485,
          "z": -61.248
        },
        {
          "x": -285.495,
          "z": -59.935
        },
        {
          "x": -287.433,
          "z": -59.946
        },
        {
          "x": -287.488,
          "z": -51.886
        },
        {
          "x": -260.509,
          "z": -51.708
        }
      ],
      "height_m": 9.4,
      "id": "way/407024555",
      "levels": 0,
      "name": null
    },
    {
      "building": "apartments",
      "footprint": [
        {
          "x": -372.654,
          "z": -68.072
        },
        {
          "x": -366.59,
          "z": -68.128
        },
        {
          "x": -366.599,
          "z": -69.953
        },
        {
          "x": -365.621,
          "z": -69.953
        },
        {
          "x": -365.621,
          "z": -70.31
        },
        {
          "x": -362.187,
          "z": -70.332
        },
        {
          "x": -362.169,
          "z": -67.972
        },
        {
          "x": -354.535,
          "z": -68.039
        },
        {
          "x": -354.545,
          "z": -70.221
        },
        {
          "x": -351.268,
          "z": -70.254
        },
        {
          "x": -351.268,
          "z": -69.787
        },
        {
          "x": -349.865,
          "z": -69.798
        },
        {
          "x": -349.874,
          "z": -70.566
        },
        {
          "x": -347.484,
          "z": -70.588
        },
        {
          "x": -347.456,
          "z": -67.916
        },
        {
          "x": -337.709,
          "z": -68.005
        },
        {
          "x": -337.829,
          "z": -81.319
        },
        {
          "x": -347.474,
          "z": -81.23
        },
        {
          "x": -347.465,
          "z": -79.694
        },
        {
          "x": -347.899,
          "z": -79.694
        },
        {
          "x": -347.899,
          "z": -78.726
        },
        {
          "x": -350.105,
          "z": -78.714
        },
        {
          "x": -350.105,
          "z": -78.08
        },
        {
          "x": -358.874,
          "z": -78.002
        },
        {
          "x": -358.883,
          "z": -78.692
        },
        {
          "x": -362.935,
          "z": -78.659
        },
        {
          "x": -362.926,
          "z": -78.169
        },
        {
          "x": -365.759,
          "z": -78.147
        },
        {
          "x": -365.778,
          "z": -79.905
        },
        {
          "x": -368.15,
          "z": -79.894
        },
        {
          "x": -368.159,
          "z": -80.941
        },
        {
          "x": -370.116,
          "z": -80.93
        },
        {
          "x": -370.116,
          "z": -80.006
        },
        {
          "x": -372.756,
          "z": -79.983
        },
        {
          "x": -372.654,
          "z": -68.072
        }
      ],
      "height_m": 5.1,
      "id": "way/407024560",
      "levels": 0,
      "name": null
    },
    {
      "building": "apartments",
      "footprint": [
        {
          "x": -372.691,
          "z": -54.346
        },
        {
          "x": -370.014,
          "z": -54.324
        },
        {
          "x": -370.023,
          "z": -53.211
        },
        {
          "x": -368.159,
          "z": -53.2
        },
        {
          "x": -368.15,
          "z": -54.324
        },
        {
          "x": -365.888,
          "z": -54.313
        },
        {
          "x": -365.888,
          "z": -56.128
        },
        {
          "x": -362.916,
          "z": -56.116
        },
        {
          "x": -362.926,
          "z": -55.46
        },
        {
          "x": -359.104,
          "z": -55.437
        },
        {
          "x": -359.104,
          "z": -56.094
        },
        {
          "x": -349.994,
          "z": -56.05
        },
        {
          "x": -349.994,
          "z": -55.326
        },
        {
          "x": -347.89,
          "z": -55.315
        },
        {
          "x": -347.899,
          "z": -54.458
        },
        {
          "x": -347.484,
          "z": -54.458
        },
        {
          "x": -347.493,
          "z": -52.643
        },
        {
          "x": -339.047,
          "z": -52.599
        },
        {
          "x": -339.047,
          "z": -52.933
        },
        {
          "x": -337.82,
          "z": -52.933
        },
        {
          "x": -337.755,
          "z": -65.935
        },
        {
          "x": -347.502,
          "z": -65.979
        },
        {
          "x": -347.511,
          "z": -63.553
        },
        {
          "x": -349.68,
          "z": -63.564
        },
        {
          "x": -349.68,
          "z": -64.265
        },
        {
          "x": -351.176,
          "z": -64.276
        },
        {
          "x": -351.176,
          "z": -63.898
        },
        {
          "x": -354.48,
          "z": -63.909
        },
        {
          "x": -354.471,
          "z": -66.102
        },
        {
          "x": -362.123,
          "z": -66.135
        },
        {
          "x": -362.132,
          "z": -63.953
        },
        {
          "x": -366.535,
          "z": -63.976
        },
        {
          "x": -366.525,
          "z": -66.135
        },
        {
          "x": -372.636,
          "z": -66.169
        },
        {
          "x": -372.691,
          "z": -54.346
        }
      ],
      "height_m": 5.1,
      "id": "way/407024563",
      "levels": 0,
      "name": null
    },
    {
      "building": "apartments",
      "footprint": [
        {
          "x": -372.617,
          "z": -37.37
        },
        {
          "x": -366.535,
          "z": -37.337
        },
        {
          "x": -366.525,
          "z": -39.263
        },
        {
          "x": -365.584,
          "z": -39.263
        },
        {
          "x": -365.575,
          "z": -39.608
        },
        {
          "x": -362.159,
          "z": -39.585
        },
        {
          "x": -362.169,
          "z": -37.37
        },
        {
          "x": -354.48,
          "z": -37.337
        },
        {
          "x": -354.471,
          "z": -39.619
        },
        {
          "x": -351.102,
          "z": -39.597
        },
        {
          "x": -351.102,
          "z": -39.174
        },
        {
          "x": -349.727,
          "z": -39.162
        },
        {
          "x": -349.727,
          "z": -40.008
        },
        {
          "x": -347.428,
          "z": -39.997
        },
        {
          "x": -347.438,
          "z": -37.415
        },
        {
          "x": -337.801,
          "z": -37.37
        },
        {
          "x": -337.746,
          "z": -50.573
        },
        {
          "x": -347.336,
          "z": -50.606
        },
        {
          "x": -347.345,
          "z": -48.992
        },
        {
          "x": -347.751,
          "z": -48.992
        },
        {
          "x": -347.751,
          "z": -48.113
        },
        {
          "x": -349.865,
          "z": -48.124
        },
        {
          "x": -349.865,
          "z": -47.378
        },
        {
          "x": -359.067,
          "z": -47.411
        },
        {
          "x": -359.067,
          "z": -47.979
        },
        {
          "x": -362.852,
          "z": -48.001
        },
        {
          "x": -362.852,
          "z": -47.378
        },
        {
          "x": -365.768,
          "z": -47.389
        },
        {
          "x": -365.759,
          "z": -49.248
        },
        {
          "x": -368.196,
          "z": -49.259
        },
        {
          "x": -368.196,
          "z": -50.127
        },
        {
          "x": -370.023,
          "z": -50.139
        },
        {
          "x": -370.023,
          "z": -49.27
        },
        {
          "x": -372.571,
          "z": -49.281
        },
        {
          "x": -372.617,
          "z": -37.37
        }
      ],
      "height_m": 5.2,
      "id": "way/407024566",
      "levels": 0,
      "name": null
    },
    {
      "building": "residential",
      "footprint": [
        {
          "x": -354.988,
          "z": -118.745
        },
        {
          "x": -360.664,
          "z": -118.812
        },
        {
          "x": -360.729,
          "z": -112.834
        },
        {
          "x": -355.052,
          "z": -112.778
        },
        {
          "x": -354.988,
          "z": -118.745
        }
      ],
      "height_m": 3.1,
      "id": "way/407024605",
      "levels": 0,
      "name": null
    },
    {
      "building": "commercial",
      "footprint": [
        {
          "x": -189.364,
          "z": -3.841
        },
        {
          "x": -181.02,
          "z": -3.796
        },
        {
          "x": -181.038,
          "z": -23.366
        },
        {
          "x": -189.474,
          "z": -23.322
        },
        {
          "x": -189.364,
          "z": -3.841
        }
      ],
      "height_m": 4.7,
      "id": "way/407024618",
      "levels": 0,
      "name": null
    },
    {
      "building": "residential",
      "footprint": [
        {
          "x": -190.776,
          "z": -131.914
        },
        {
          "x": -190.721,
          "z": -137.781
        },
        {
          "x": -194.976,
          "z": -137.825
        },
        {
          "x": -195.031,
          "z": -131.959
        },
        {
          "x": -190.776,
          "z": -131.914
        }
      ],
      "height_m": 2.8,
      "id": "way/407024621",
      "levels": 0,
      "name": null
    },
    {
      "building": "residential",
      "footprint": [
        {
          "x": -251.408,
          "z": -39.352
        },
        {
          "x": -257.334,
          "z": -39.34
        },
        {
          "x": -257.315,
          "z": -31.904
        },
        {
          "x": -251.39,
          "z": -31.915
        },
        {
          "x": -251.408,
          "z": -39.352
        }
      ],
      "height_m": 4.6,
      "id": "way/407024650",
      "levels": 0,
      "name": null
    },
    {
      "building": "residential",
      "footprint": [
        {
          "x": -227.207,
          "z": -38.784
        },
        {
          "x": -234.314,
          "z": -38.873
        },
        {
          "x": -234.416,
          "z": -31.192
        },
        {
          "x": -227.308,
          "z": -31.103
        },
        {
          "x": -227.207,
          "z": -38.784
        }
      ],
      "height_m": 4.5,
      "id": "way/407024685",
      "levels": 0,
      "name": null
    },
    {
      "building": "house",
      "footprint": [
        {
          "x": -190.573,
          "z": -48.402
        },
        {
          "x": -194.874,
          "z": -48.391
        },
        {
          "x": -194.846,
          "z": -42.201
        },
        {
          "x": -190.554,
          "z": -42.213
        },
        {
          "x": -190.573,
          "z": -48.402
        }
      ],
      "height_m": 3.7,
      "id": "way/407024711",
      "levels": 0,
      "name": null
    },
    {
      "building": "house",
      "footprint": [
        {
          "x": -213.159,
          "z": -140.363
        },
        {
          "x": -213.251,
          "z": -133.751
        },
        {
          "x": -206.162,
          "z": -133.651
        },
        {
          "x": -206.07,
          "z": -140.263
        },
        {
          "x": -213.159,
          "z": -140.363
        }
      ],
      "height_m": 4.9,
      "id": "way/407024756",
      "levels": 0,
      "name": null
    },
    {
      "building": "house",
      "footprint": [
        {
          "x": -251.51,
          "z": -132.86
        },
        {
          "x": -251.547,
          "z": -139.618
        },
        {
          "x": -259.475,
          "z": -139.584
        },
        {
          "x": -259.447,
          "z": -132.816
        },
        {
          "x": -251.51,
          "z": -132.86
        }
      ],
      "height_m": 5.5,
      "id": "way/407024819",
      "levels": 0,
      "name": null
    },
    {
      "building": "house",
      "footprint": [
        {
          "x": -232.634,
          "z": -136.289
        },
        {
          "x": -232.653,
          "z": -140.942
        },
        {
          "x": -235.708,
          "z": -140.931
        },
        {
          "x": -235.689,
          "z": -136.267
        },
        {
          "x": -232.634,
          "z": -136.289
        }
      ],
      "height_m": 4.1,
      "id": "way/407024845",
      "levels": 0,
      "name": null
    },
    {
      "building": "commercial",
      "footprint": [
        {
          "x": -337.783,
          "z": -163.273
        },
        {
          "x": -342.453,
          "z": -163.273
        },
        {
          "x": -342.444,
          "z": -156.683
        },
        {
          "x": -337.783,
          "z": -156.683
        },
        {
          "x": -337.783,
          "z": -163.273
        }
      ],
      "height_m": 3.8,
      "id": "way/407024847",
      "levels": 0,
      "name": null
    },
    {
      "building": "apartments",
      "footprint": [
        {
          "x": -280.953,
          "z": -39.808
        },
        {
          "x": -288.384,
          "z": -39.786
        },
        {
          "x": -288.356,
          "z": -22.62
        },
        {
          "x": -280.87,
          "z": -22.709
        },
        {
          "x": -280.953,
          "z": -39.808
        }
      ],
      "height_m": 2.8,
      "id": "way/407024852",
      "levels": 0,
      "name": null
    },
    {
      "building": "house",
      "footprint": [
        {
          "x": -210.03,
          "z": -48.524
        },
        {
          "x": -210.011,
          "z": -43.816
        },
        {
          "x": -205.765,
          "z": -43.827
        },
        {
          "x": -205.775,
          "z": -48.536
        },
        {
          "x": -210.03,
          "z": -48.524
        }
      ],
      "height_m": 4.1,
      "id": "way/407024885",
      "levels": 0,
      "name": null
    },
    {
      "building": "industrial",
      "footprint": [
        {
          "x": -336.601,
          "z": -119.09
        },
        {
          "x": -336.601,
          "z": -119.892
        },
        {
          "x": -344.216,
          "z": -119.869
        },
        {
          "x": -344.207,
          "z": -119.157
        },
        {
          "x": -344.207,
          "z": -118.767
        },
        {
          "x": -353.336,
          "z": -118.734
        },
        {
          "x": -353.372,
          "z": -101.201
        },
        {
          "x": -336.565,
          "z": -101.045
        },
        {
          "x": -336.601,
          "z": -119.09
        }
      ],
      "height_m": 5.0,
      "id": "way/407024893",
      "levels": 0,
      "name": null
    },
    {
      "building": "retail",
      "footprint": [
        {
          "x": -195.216,
          "z": -39.652
        },
        {
          "x": -195.326,
          "z": -36.424
        },
        {
          "x": -192.031,
          "z": -36.313
        },
        {
          "x": -191.92,
          "z": -39.541
        },
        {
          "x": -195.216,
          "z": -39.652
        }
      ],
      "height_m": 3.2,
      "id": "way/407024895",
      "levels": 0,
      "name": null
    },
    {
      "building": "residential",
      "footprint": [
        {
          "x": -206.578,
          "z": -151.006
        },
        {
          "x": -212.439,
          "z": -151.006
        },
        {
          "x": -212.439,
          "z": -141.265
        },
        {
          "x": -206.569,
          "z": -141.265
        },
        {
          "x": -206.578,
          "z": -151.006
        }
      ],
      "height_m": 5.1,
      "id": "way/407024903",
      "levels": 0,
      "name": null
    },
    {
      "building": "house",
      "footprint": [
        {
          "x": -243.516,
          "z": -141.621
        },
        {
          "x": -236.834,
          "z": -141.599
        },
        {
          "x": -236.815,
          "z": -148.412
        },
        {
          "x": -243.489,
          "z": -148.434
        },
        {
          "x": -243.516,
          "z": -141.621
        }
      ],
      "height_m": 3.5,
      "id": "way/407024927",
      "levels": 0,
      "name": null
    },
    {
      "building": "house",
      "footprint": [
        {
          "x": -221.309,
          "z": -151.84
        },
        {
          "x": -228.093,
          "z": -151.963
        },
        {
          "x": -228.231,
          "z": -144.738
        },
        {
          "x": -221.438,
          "z": -144.605
        },
        {
          "x": -221.309,
          "z": -151.84
        }
      ],
      "height_m": 4.0,
      "id": "way/407024936",
      "levels": 0,
      "name": null
    },
    {
      "building": "house",
      "footprint": [
        {
          "x": -263.13,
          "z": -126.782
        },
        {
          "x": -265.936,
          "z": -126.749
        },
        {
          "x": -265.918,
          "z": -122.419
        },
        {
          "x": -263.149,
          "z": -122.452
        },
        {
          "x": -263.13,
          "z": -126.782
        }
      ],
      "height_m": 2.8,
      "id": "way/407024945",
      "levels": 0,
      "name": null
    },
    {
      "building": "house",
      "footprint": [
        {
          "x": -225.361,
          "z": -72.469
        },
        {
          "x": -233.908,
          "z": -72.391
        },
        {
          "x": -233.769,
          "z": -57.497
        },
        {
          "x": -228.407,
          "z": -57.541
        },
        {
          "x": -228.388,
          "z": -56.283
        },
        {
          "x": -225.213,
          "z": -56.306
        },
        {
          "x": -225.361,
          "z": -72.469
        }
      ],
      "height_m": 6.0,
      "id": "way/407024998",
      "levels": 0,
      "name": null
    },
    {
      "building": "house",
      "footprint": [
        {
          "x": -225.389,
          "z": -123.899
        },
        {
          "x": -228.582,
          "z": -123.921
        },
        {
          "x": -228.582,
          "z": -122.307
        },
        {
          "x": -234.166,
          "z": -122.33
        },
        {
          "x": -234.213,
          "z": -108.448
        },
        {
          "x": -225.444,
          "z": -108.415
        },
        {
          "x": -225.389,
          "z": -123.899
        }
      ],
      "height_m": 6.1,
      "id": "way/407025024",
      "levels": 0,
      "name": null
    },
    {
      "building": "residential",
      "footprint": [
        {
          "x": -201.381,
          "z": -152.041
        },
        {
          "x": -201.474,
          "z": -144.883
        },
        {
          "x": -192.29,
          "z": -144.749
        },
        {
          "x": -192.271,
          "z": -146.564
        },
        {
          "x": -193.462,
          "z": -146.575
        },
        {
          "x": -193.388,
          "z": -151.918
        },
        {
          "x": -201.381,
          "z": -152.041
        }
      ],
      "height_m": 7.2,
      "id": "way/407025039",
      "levels": 0,
      "name": null
    },
    {
      "building": "yes",
      "footprint": [
        {
          "x": -295.122,
          "z": -59.501
        },
        {
          "x": -309.788,
          "z": -59.501
        },
        {
          "x": -309.844,
          "z": -40.799
        },
        {
          "x": -299.524,
          "z": -40.71
        },
        {
          "x": -299.543,
          "z": -45.073
        },
        {
          "x": -295.122,
          "z": -45.073
        },
        {
          "x": -295.122,
          "z": -59.501
        }
      ],
      "height_m": 3.5,
      "id": "way/407025044",
      "levels": 0,
      "name": null
    },
    {
      "building": "yes",
      "footprint": [
        {
          "x": -266.158,
          "z": -147.61
        },
        {
          "x": -266.361,
          "z": -147.61
        },
        {
          "x": -266.361,
          "z": -147.21
        },
        {
          "x": -269.674,
          "z": -147.232
        },
        {
          "x": -269.702,
          "z": -141.777
        },
        {
          "x": -266.176,
          "z": -141.766
        },
        {
          "x": -266.158,
          "z": -147.61
        }
      ],
      "height_m": 3.9,
      "id": "way/407025073",
      "levels": 0,
      "name": null
    },
    {
      "building": "house",
      "footprint": [
        {
          "x": -181.85,
          "z": -127.706
        },
        {
          "x": -188.339,
          "z": -127.684
        },
        {
          "x": -188.302,
          "z": -108.103
        },
        {
          "x": -179.709,
          "z": -108.114
        },
        {
          "x": -179.737,
          "z": -124.155
        },
        {
          "x": -181.841,
          "z": -124.144
        },
        {
          "x": -181.841,
          "z": -126.148
        },
        {
          "x": -181.85,
          "z": -127.706
        }
      ],
      "height_m": 4.6,
      "id": "way/407025086",
      "levels": 0,
      "name": null
    },
    {
      "building": "commercial",
      "footprint": [
        {
          "x": -347.345,
          "z": -151.228
        },
        {
          "x": -347.345,
          "z": -158.408
        },
        {
          "x": -346.395,
          "z": -158.408
        },
        {
          "x": -346.395,
          "z": -162.405
        },
        {
          "x": -361.126,
          "z": -162.394
        },
        {
          "x": -361.126,
          "z": -162.705
        },
        {
          "x": -369.027,
          "z": -162.694
        },
        {
          "x": -369.017,
          "z": -151.206
        },
        {
          "x": -347.345,
          "z": -151.228
        }
      ],
      "height_m": 4.4,
      "id": "way/407025106",
      "levels": 0,
      "name": null
    },
    {
      "building": "house",
      "footprint": [
        {
          "x": -179.617,
          "z": -72.102
        },
        {
          "x": -188.321,
          "z": -72.08
        },
        {
          "x": -188.284,
          "z": -57.987
        },
        {
          "x": -187.785,
          "z": -57.987
        },
        {
          "x": -187.776,
          "z": -54.102
        },
        {
          "x": -184.103,
          "z": -54.113
        },
        {
          "x": -184.112,
          "z": -56.473
        },
        {
          "x": -179.58,
          "z": -56.484
        },
        {
          "x": -179.617,
          "z": -72.102
        }
      ],
      "height_m": 6.0,
      "id": "way/407025133",
      "levels": 0,
      "name": null
    },
    {
      "building": "house",
      "footprint": [
        {
          "x": -177.06,
          "z": -148.178
        },
        {
          "x": -182.34,
          "z": -148.178
        },
        {
          "x": -182.34,
          "z": -148.445
        },
        {
          "x": -189.031,
          "z": -148.445
        },
        {
          "x": -189.031,
          "z": -141.733
        },
        {
          "x": -182.441,
          "z": -141.733
        },
        {
          "x": -182.441,
          "z": -141.989
        },
        {
          "x": -177.06,
          "z": -141.989
        },
        {
          "x": -177.06,
          "z": -148.178
        }
      ],
      "height_m": 4.1,
      "id": "way/407025140",
      "levels": 0,
      "name": null
    },
    {
      "building": "house",
      "footprint": [
        {
          "x": -210.224,
          "z": -72.247
        },
        {
          "x": -218.734,
          "z": -72.158
        },
        {
          "x": -218.586,
          "z": -58.343
        },
        {
          "x": -217.949,
          "z": -58.343
        },
        {
          "x": -217.931,
          "z": -55.949
        },
        {
          "x": -217.469,
          "z": -55.961
        },
        {
          "x": -217.423,
          "z": -52.165
        },
        {
          "x": -210.021,
          "z": -52.242
        },
        {
          "x": -210.224,
          "z": -72.247
        }
      ],
      "height_m": 6.4,
      "id": "way/407025148",
      "levels": 0,
      "name": null
    },
    {
      "building": "apartments",
      "footprint": [
        {
          "x": -280.114,
          "z": -19.47
        },
        {
          "x": -288.476,
          "z": -19.459
        },
        {
          "x": -288.458,
          "z": -13.581
        },
        {
          "x": -287.664,
          "z": -13.626
        },
        {
          "x": -287.682,
          "z": -9.874
        },
        {
          "x": -288.421,
          "z": -9.807
        },
        {
          "x": -288.31,
          "z": -4.553
        },
        {
          "x": -280.16,
          "z": -4.486
        },
        {
          "x": -280.114,
          "z": -19.47
        }
      ],
      "height_m": 8.7,
      "id": "way/407025154",
      "levels": 0,
      "name": null
    },
    {
      "building": "house",
      "footprint": [
        {
          "x": -251.787,
          "z": -141.71
        },
        {
          "x": -251.768,
          "z": -148.735
        },
        {
          "x": -257.989,
          "z": -148.757
        },
        {
          "x": -257.989,
          "z": -149.08
        },
        {
          "x": -263.481,
          "z": -149.091
        },
        {
          "x": -263.481,
          "z": -147.599
        },
        {
          "x": -266.158,
          "z": -147.61
        },
        {
          "x": -266.176,
          "z": -141.766
        },
        {
          "x": -251.787,
          "z": -141.71
        }
      ],
      "height_m": 3.8,
      "id": "way/407025163",
      "levels": 0,
      "name": null
    },
    {
      "building": "commercial",
      "footprint": [
        {
          "x": -354.499,
          "z": -147.833
        },
        {
          "x": -354.48,
          "z": -149.38
        },
        {
          "x": -365.962,
          "z": -149.525
        },
        {
          "x": -366.036,
          "z": -143.536
        },
        {
          "x": -350.022,
          "z": -143.336
        },
        {
          "x": -350.031,
          "z": -142.222
        },
        {
          "x": -336.74,
          "z": -142.145
        },
        {
          "x": -336.694,
          "z": -147.61
        },
        {
          "x": -354.499,
          "z": -147.833
        }
      ],
      "height_m": 3.7,
      "id": "way/407025165",
      "levels": 0,
      "name": null
    },
    {
      "building": "residential",
      "footprint": [
        {
          "x": -235.708,
          "z": -140.931
        },
        {
          "x": -236.428,
          "z": -140.92
        },
        {
          "x": -236.418,
          "z": -138.104
        },
        {
          "x": -241.8,
          "z": -138.07
        },
        {
          "x": -241.772,
          "z": -132.215
        },
        {
          "x": -236.455,
          "z": -132.248
        },
        {
          "x": -236.483,
          "z": -136.267
        },
        {
          "x": -235.689,
          "z": -136.267
        },
        {
          "x": -235.708,
          "z": -140.931
        }
      ],
      "height_m": 4.3,
      "id": "way/407025167",
      "levels": 0,
      "name": null
    },
    {
      "building": "residential",
      "footprint": [
        {
          "x": -265.078,
          "z": -7.47
        },
        {
          "x": -255.303,
          "z": -7.514
        },
        {
          "x": -255.368,
          "z": -23.032
        },
        {
          "x": -256.568,
          "z": -23.032
        },
        {
          "x": -256.577,
          "z": -24.824
        },
        {
          "x": -259.272,
          "z": -24.813
        },
        {
          "x": -259.3,
          "z": -29.722
        },
        {
          "x": -265.179,
          "z": -29.689
        },
        {
          "x": -265.078,
          "z": -7.47
        }
      ],
      "height_m": 6.4,
      "id": "way/407025173",
      "levels": 0,
      "name": null
    },
    {
      "building": "house",
      "footprint": [
        {
          "x": -225.536,
          "z": -132.293
        },
        {
          "x": -225.536,
          "z": -132.07
        },
        {
          "x": -221.374,
          "z": -132.003
        },
        {
          "x": -221.272,
          "z": -137.937
        },
        {
          "x": -225.509,
          "z": -138.015
        },
        {
          "x": -225.518,
          "z": -137.692
        },
        {
          "x": -228.988,
          "z": -137.747
        },
        {
          "x": -229.025,
          "z": -135.254
        },
        {
          "x": -227.327,
          "z": -132.326
        },
        {
          "x": -225.536,
          "z": -132.293
        }
      ],
      "height_m": 4.4,
      "id": "way/407025213",
      "levels": 0,
      "name": null
    }
  ],
  "coord_x": -2,
  "coord_z": -1,
  "counts": {
    "areas": 1,
    "buildings": 59,
    "junctions": 16,
    "pois": 5,
    "streets": 26
  },
  "id": "-2_-1",
  "junctions": [
    {
      "connected_road_count": 2,
      "highways": [
        "secondary",
        "service"
      ],
      "id": "10010480212",
      "position": {
        "x": -322.738,
        "z": -14.917
      },
      "radius_m": 7.56
    },
    {
      "connected_road_count": 2,
      "highways": [
        "secondary",
        "service"
      ],
      "id": "11398532932",
      "position": {
        "x": -322.923,
        "z": -13.024
      },
      "radius_m": 7.56
    },
    {
      "connected_road_count": 2,
      "highways": [
        "service"
      ],
      "id": "11398532933",
      "position": {
        "x": -309.973,
        "z": -13.002
      },
      "radius_m": 3.2
    },
    {
      "connected_road_count": 3,
      "highways": [
        "service"
      ],
      "id": "11398532934",
      "position": {
        "x": -309.982,
        "z": -30.702
      },
      "radius_m": 3.2
    },
    {
      "connected_road_count": 2,
      "highways": [
        "service"
      ],
      "id": "11398532935",
      "position": {
        "x": -294.42,
        "z": -30.68
      },
      "radius_m": 3.2
    },
    {
      "connected_road_count": 2,
      "highways": [
        "secondary",
        "service"
      ],
      "id": "11398532938",
      "position": {
        "x": -322.766,
        "z": -30.602
      },
      "radius_m": 4.976
    },
    {
      "connected_road_count": 2,
      "highways": [
        "service"
      ],
      "id": "11398532939",
      "position": {
        "x": -308.413,
        "z": -11.767
      },
      "radius_m": 3.2
    },
    {
      "connected_road_count": 3,
      "highways": [
        "service"
      ],
      "id": "11398532942",
      "position": {
        "x": -293.313,
        "z": -13.971
      },
      "radius_m": 3.2
    },
    {
      "connected_road_count": 2,
      "highways": [
        "service"
      ],
      "id": "11398532943",
      "position": {
        "x": -295.842,
        "z": -11.31
      },
      "radius_m": 3.2
    },
    {
      "connected_road_count": 4,
      "highways": [
        "residential",
        "secondary"
      ],
      "id": "123224180",
      "position": {
        "x": -322.941,
        "z": -91.461
      },
      "radius_m": 4.976
    },
    {
      "connected_road_count": 2,
      "highways": [
        "secondary"
      ],
      "id": "4011301815",
      "position": {
        "x": -322.849,
        "z": -53.968
      },
      "radius_m": 4.976
    },
    {
      "connected_road_count": 2,
      "highways": [
        "secondary"
      ],
      "id": "4011301818",
      "position": {
        "x": -322.766,
        "z": -23.867
      },
      "radius_m": 7.56
    },
    {
      "connected_road_count": 2,
      "highways": [
        "residential",
        "service"
      ],
      "id": "6768739143",
      "position": {
        "x": -274.769,
        "z": -90.737
      },
      "radius_m": 3.684
    },
    {
      "connected_road_count": 2,
      "highways": [
        "secondary",
        "service"
      ],
      "id": "6768739144",
      "position": {
        "x": -323.015,
        "z": -167.971
      },
      "radius_m": 4.976
    },
    {
      "connected_road_count": 2,
      "highways": [
        "service"
      ],
      "id": "6768739147",
      "position": {
        "x": -274.04,
        "z": -160.902
      },
      "radius_m": 3.2
    },
    {
      "connected_road_count": 2,
      "highways": [
        "secondary",
        "service"
      ],
      "id": "8461070853",
      "position": {
        "x": -322.784,
        "z": -135.866
      },
      "radius_m": 4.976
    }
  ],
  "pois": [
    {
      "amenity": "place_of_worship",
      "bus": null,
      "crossing": null,
      "highway": null,
      "id": "node/358850602",
      "name": "Ascension Lutheran Church",
      "position": {
        "x": -312.29,
        "z": -63.931
      },
      "public_transport": null,
      "shop": null
    },
    {
      "amenity": "school",
      "bus": null,
      "crossing": null,
      "highway": null,
      "id": "node/358850603",
      "name": "Ascension Lutheran School",
      "position": {
        "x": -286.648,
        "z": -63.931
      },
      "public_transport": null,
      "shop": null
    },
    {
      "amenity": "place_of_worship",
      "bus": null,
      "crossing": null,
      "highway": null,
      "id": "node/358850610",
      "name": "First Church of God",
      "position": {
        "x": -312.29,
        "z": -94.845
      },
      "public_transport": null,
      "shop": null
    },
    {
      "amenity": null,
      "bus": "yes",
      "crossing": null,
      "highway": "bus_stop",
      "id": "node/10010480211",
      "name": "Slauson & West",
      "position": {
        "x": -346.468,
        "z": -2.238
      },
      "public_transport": "platform",
      "shop": null
    },
    {
      "amenity": null,
      "bus": null,
      "crossing": null,
      "highway": null,
      "id": "node/13963337812",
      "name": "S\u00dcPRMARKT",
      "position": {
        "x": -213.823,
        "z": -15.885
      },
      "public_transport": null,
      "shop": "greengrocer"
    }
  ],
  "schema": "gangland.unity_city_chunk.v1",
  "streets": [
    {
      "centerline": [
        {
          "x": -322.941,
          "z": -91.461
        },
        {
          "x": -337.211,
          "z": -91.594
        },
        {
          "x": -383.555,
          "z": -92.028
        }
      ],
      "crossing": null,
      "end_node_id": "705825474",
      "estimated_road_width_m": 6.8,
      "highway": "residential",
      "id": "way/295757630#section/0",
      "lane_count": 2,
      "lane_source": "inferred",
      "lane_width_m": 3.4,
      "maxspeed": null,
      "name": "West 58th Place",
      "oneway": false,
      "parent_id": "way/295757630",
      "render_kind": "road",
      "road_width_m": 6.8,
      "section_index": 0,
      "start_node_id": "123224180",
      "surface": "asphalt",
      "trim_end_m": 0,
      "trim_start_m": 0,
      "turn_lanes": null
    },
    {
      "centerline": [
        {
          "x": -322.766,
          "z": -23.867
        },
        {
          "x": -322.766,
          "z": -30.602
        }
      ],
      "crossing": null,
      "end_node_id": "11398532938",
      "estimated_road_width_m": 10.2,
      "highway": "secondary",
      "id": "way/398367007#section/0",
      "lane_count": 3,
      "lane_source": "osm",
      "lane_width_m": 3.4,
      "maxspeed": "30 mph",
      "name": "West Boulevard",
      "oneway": false,
      "parent_id": "way/398367007",
      "render_kind": "road",
      "road_width_m": 10.2,
      "section_index": 0,
      "start_node_id": "4011301818",
      "surface": "asphalt",
      "trim_end_m": 0,
      "trim_start_m": 0,
      "turn_lanes": null
    },
    {
      "centerline": [
        {
          "x": -322.766,
          "z": -30.602
        },
        {
          "x": -322.849,
          "z": -53.968
        }
      ],
      "crossing": null,
      "end_node_id": "4011301815",
      "estimated_road_width_m": 10.2,
      "highway": "secondary",
      "id": "way/398367007#section/1",
      "lane_count": 3,
      "lane_source": "osm",
      "lane_width_m": 3.4,
      "maxspeed": "30 mph",
      "name": "West Boulevard",
      "oneway": false,
      "parent_id": "way/398367007",
      "render_kind": "road",
      "road_width_m": 10.2,
      "section_index": 1,
      "start_node_id": "11398532938",
      "surface": "asphalt",
      "trim_end_m": 0,
      "trim_start_m": 0,
      "turn_lanes": null
    },
    {
      "centerline": [
        {
          "x": -322.849,
          "z": -53.968
        },
        {
          "x": -322.941,
          "z": -91.461
        }
      ],
      "crossing": null,
      "end_node_id": "123224180",
      "estimated_road_width_m": 10.2,
      "highway": "secondary",
      "id": "way/398367010#section/0",
      "lane_count": 3,
      "lane_source": "osm",
      "lane_width_m": 3.4,
      "maxspeed": "30 mph",
      "name": "West Boulevard",
      "oneway": false,
      "parent_id": "way/398367010",
      "render_kind": "road",
      "road_width_m": 10.2,
      "section_index": 0,
      "start_node_id": "4011301815",
      "surface": "asphalt",
      "trim_end_m": 0,
      "trim_start_m": 0,
      "turn_lanes": null
    },
    {
      "centerline": [
        {
          "x": -325.701,
          "z": 7.225
        },
        {
          "x": -322.923,
          "z": -13.024
        }
      ],
      "crossing": null,
      "end_node_id": "11398532932",
      "estimated_road_width_m": 17.0,
      "highway": "secondary",
      "id": "way/398367012#section/0",
      "lane_count": 5,
      "lane_source": "osm",
      "lane_width_m": 3.4,
      "maxspeed": "30 mph",
      "name": "West Boulevard",
      "oneway": false,
      "parent_id": "way/398367012",
      "render_kind": "road",
      "road_width_m": 17.0,
      "section_index": 0,
      "start_node_id": "123224179",
      "surface": "asphalt",
      "trim_end_m": 0,
      "trim_start_m": 0,
      "turn_lanes": null
    },
    {
      "centerline": [
        {
          "x": -322.923,
          "z": -13.024
        },
        {
          "x": -322.738,
          "z": -14.917
        }
      ],
      "crossing": null,
      "end_node_id": "10010480212",
      "estimated_road_width_m": 17.0,
      "highway": "secondary",
      "id": "way/398367012#section/1",
      "lane_count": 5,
      "lane_source": "osm",
      "lane_width_m": 3.4,
      "maxspeed": "30 mph",
      "name": "West Boulevard",
      "oneway": false,
      "parent_id": "way/398367012",
      "render_kind": "road",
      "road_width_m": 17.0,
      "section_index": 1,
      "start_node_id": "11398532932",
      "surface": "asphalt",
      "trim_end_m": 0,
      "trim_start_m": 0,
      "turn_lanes": null
    },
    {
      "centerline": [
        {
          "x": -322.738,
          "z": -14.917
        },
        {
          "x": -322.766,
          "z": -23.867
        }
      ],
      "crossing": null,
      "end_node_id": "4011301818",
      "estimated_road_width_m": 17.0,
      "highway": "secondary",
      "id": "way/398367012#section/2",
      "lane_count": 5,
      "lane_source": "osm",
      "lane_width_m": 3.4,
      "maxspeed": "30 mph",
      "name": "West Boulevard",
      "oneway": false,
      "parent_id": "way/398367012",
      "render_kind": "road",
      "road_width_m": 17.0,
      "section_index": 2,
      "start_node_id": "10010480212",
      "surface": "asphalt",
      "trim_end_m": 0,
      "trim_start_m": 0,
      "turn_lanes": null
    },
    {
      "centerline": [
        {
          "x": -322.941,
          "z": -91.461
        },
        {
          "x": -322.821,
          "z": -132.415
        },
        {
          "x": -322.784,
          "z": -135.866
        }
      ],
      "crossing": null,
      "end_node_id": "8461070853",
      "estimated_road_width_m": 10.2,
      "highway": "secondary",
      "id": "way/398367013#section/0",
      "lane_count": 3,
      "lane_source": "osm",
      "lane_width_m": 3.4,
      "maxspeed": "30 mph",
      "name": "West Boulevard",
      "oneway": false,
      "parent_id": "way/398367013",
      "render_kind": "road",
      "road_width_m": 10.2,
      "section_index": 0,
      "start_node_id": "123224180",
      "surface": "asphalt",
      "trim_end_m": 0,
      "trim_start_m": 0,
      "turn_lanes": null
    },
    {
      "centerline": [
        {
          "x": -322.784,
          "z": -135.866
        },
        {
          "x": -323.015,
          "z": -167.971
        }
      ],
      "crossing": null,
      "end_node_id": "6768739144",
      "estimated_road_width_m": 10.2,
      "highway": "secondary",
      "id": "way/398367013#section/1",
      "lane_count": 3,
      "lane_source": "osm",
      "lane_width_m": 3.4,
      "maxspeed": "30 mph",
      "name": "West Boulevard",
      "oneway": false,
      "parent_id": "way/398367013",
      "render_kind": "road",
      "road_width_m": 10.2,
      "section_index": 1,
      "start_node_id": "8461070853",
      "surface": "asphalt",
      "trim_end_m": 0,
      "trim_start_m": 0,
      "turn_lanes": null
    },
    {
      "centerline": [
        {
          "x": -273.357,
          "z": -193.318
        },
        {
          "x": -273.865,
          "z": -181.997
        },
        {
          "x": -274.04,
          "z": -160.902
        }
      ],
      "crossing": null,
      "end_node_id": "6768739147",
      "estimated_road_width_m": 3.4,
      "highway": "service",
      "id": "way/721532885#section/0",
      "lane_count": 1,
      "lane_source": "inferred",
      "lane_width_m": 3.4,
      "maxspeed": null,
      "name": null,
      "oneway": true,
      "parent_id": "way/721532885",
      "render_kind": "road",
      "road_width_m": 3.4,
      "section_index": 0,
      "start_node_id": "6768739140",
      "surface": null,
      "trim_end_m": 0,
      "trim_start_m": 0,
      "turn_lanes": null
    },
    {
      "centerline": [
        {
          "x": -274.04,
          "z": -160.902
        },
        {
          "x": -274.52,
          "z": -100.388
        },
        {
          "x": -274.769,
          "z": -90.737
        }
      ],
      "crossing": null,
      "end_node_id": "6768739143",
      "estimated_road_width_m": 3.4,
      "highway": "service",
      "id": "way/721532885#section/1",
      "lane_count": 1,
      "lane_source": "inferred",
      "lane_width_m": 3.4,
      "maxspeed": null,
      "name": null,
      "oneway": true,
      "parent_id": "way/721532885",
      "render_kind": "road",
      "road_width_m": 3.4,
      "section_index": 1,
      "start_node_id": "6768739147",
      "surface": null,
      "trim_end_m": 0,
      "trim_start_m": 0,
      "turn_lanes": null
    },
    {
      "centerline": [
        {
          "x": -323.015,
          "z": -167.971
        },
        {
          "x": -312.216,
          "z": -167.169
        },
        {
          "x": -306.862,
          "z": -160.802
        },
        {
          "x": -274.04,
          "z": -160.902
        }
      ],
      "crossing": null,
      "end_node_id": "6768739147",
      "estimated_road_width_m": 3.4,
      "highway": "service",
      "id": "way/721532886#section/0",
      "lane_count": 1,
      "lane_source": "inferred",
      "lane_width_m": 3.4,
      "maxspeed": null,
      "name": null,
      "oneway": false,
      "parent_id": "way/721532886",
      "render_kind": "road",
      "road_width_m": 3.4,
      "section_index": 0,
      "start_node_id": "6768739144",
      "surface": null,
      "trim_end_m": 0,
      "trim_start_m": 0,
      "turn_lanes": null
    },
    {
      "centerline": [
        {
          "x": -322.784,
          "z": -135.866
        },
        {
          "x": -333.519,
          "z": -135.699
        },
        {
          "x": -363.812,
          "z": -135.254
        }
      ],
      "crossing": null,
      "end_node_id": "8461070854",
      "estimated_road_width_m": 3.4,
      "highway": "service",
      "id": "way/911219369#section/0",
      "lane_count": 1,
      "lane_source": "inferred",
      "lane_width_m": 3.4,
      "maxspeed": null,
      "name": null,
      "oneway": false,
      "parent_id": "way/911219369",
      "render_kind": "road",
      "road_width_m": 3.4,
      "section_index": 0,
      "start_node_id": "8461070853",
      "surface": null,
      "trim_end_m": 0,
      "trim_start_m": 0,
      "turn_lanes": null
    },
    {
      "centerline": [
        {
          "x": -322.738,
          "z": -14.917
        },
        {
          "x": -359.04,
          "z": -14.917
        },
        {
          "x": -359.04,
          "z": 6.768
        }
      ],
      "crossing": null,
      "end_node_id": "10010480214",
      "estimated_road_width_m": 3.4,
      "highway": "service",
      "id": "way/1093045096#section/0",
      "lane_count": 1,
      "lane_source": "inferred",
      "lane_width_m": 3.4,
      "maxspeed": null,
      "name": null,
      "oneway": false,
      "parent_id": "way/1093045096",
      "render_kind": "road",
      "road_width_m": 3.4,
      "section_index": 0,
      "start_node_id": "10010480212",
      "surface": null,
      "trim_end_m": 0,
      "trim_start_m": 0,
      "turn_lanes": null
    },
    {
      "centerline": [
        {
          "x": -293.94,
          "z": 7.28
        },
        {
          "x": -293.922,
          "z": -3.918
        },
        {
          "x": -293.912,
          "z": -9.34
        },
        {
          "x": -295.842,
          "z": -11.31
        }
      ],
      "crossing": null,
      "end_node_id": "11398532943",
      "estimated_road_width_m": 3.4,
      "highway": "service",
      "id": "way/1229118429#section/0",
      "lane_count": 1,
      "lane_source": "inferred",
      "lane_width_m": 3.4,
      "maxspeed": null,
      "name": null,
      "oneway": true,
      "parent_id": "way/1229118429",
      "render_kind": "road",
      "road_width_m": 3.4,
      "section_index": 0,
      "start_node_id": "11398532930",
      "surface": null,
      "trim_end_m": 0,
      "trim_start_m": 0,
      "turn_lanes": null
    },
    {
      "centerline": [
        {
          "x": -295.842,
          "z": -11.31
        },
        {
          "x": -308.413,
          "z": -11.767
        }
      ],
      "crossing": null,
      "end_node_id": "11398532939",
      "estimated_road_width_m": 3.4,
      "highway": "service",
      "id": "way/1229118429#section/1",
      "lane_count": 1,
      "lane_source": "inferred",
      "lane_width_m": 3.4,
      "maxspeed": null,
      "name": null,
      "oneway": true,
      "parent_id": "way/1229118429",
      "render_kind": "road",
      "road_width_m": 3.4,
      "section_index": 1,
      "start_node_id": "11398532943",
      "surface": null,
      "trim_end_m": 0,
      "trim_start_m": 0,
      "turn_lanes": null
    },
    {
      "centerline": [
        {
          "x": -308.413,
          "z": -11.767
        },
        {
          "x": -309.973,
          "z": -13.002
        }
      ],
      "crossing": null,
      "end_node_id": "11398532933",
      "estimated_road_width_m": 3.4,
      "highway": "service",
      "id": "way/1229118429#section/2",
      "lane_count": 1,
      "lane_source": "inferred",
      "lane_width_m": 3.4,
      "maxspeed": null,
      "name": null,
      "oneway": true,
      "parent_id": "way/1229118429",
      "render_kind": "road",
      "road_width_m": 3.4,
      "section_index": 2,
      "start_node_id": "11398532939",
      "surface": null,
      "trim_end_m": 0,
      "trim_start_m": 0,
      "turn_lanes": null
    },
    {
      "centerline": [
        {
          "x": -309.973,
          "z": -13.002
        },
        {
          "x": -312.409,
          "z": -13.002
        },
        {
          "x": -322.923,
          "z": -13.024
        }
      ],
      "crossing": null,
      "end_node_id": "11398532932",
      "estimated_road_width_m": 3.4,
      "highway": "service",
      "id": "way/1229118429#section/3",
      "lane_count": 1,
      "lane_source": "inferred",
      "lane_width_m": 3.4,
      "maxspeed": null,
      "name": null,
      "oneway": true,
      "parent_id": "way/1229118429",
      "render_kind": "road",
      "road_width_m": 3.4,
      "section_index": 3,
      "start_node_id": "11398532933",
      "surface": null,
      "trim_end_m": 0,
      "trim_start_m": 0,
      "turn_lanes": null
    },
    {
      "centerline": [
        {
          "x": -294.42,
          "z": -30.68
        },
        {
          "x": -291.614,
          "z": -25.181
        },
        {
          "x": -291.411,
          "z": -15.384
        },
        {
          "x": -293.313,
          "z": -13.971
        }
      ],
      "crossing": null,
      "end_node_id": "11398532942",
      "estimated_road_width_m": 3.4,
      "highway": "service",
      "id": "way/1229118430#section/0",
      "lane_count": 1,
      "lane_source": "inferred",
      "lane_width_m": 3.4,
      "maxspeed": null,
      "name": null,
      "oneway": true,
      "parent_id": "way/1229118430",
      "render_kind": "road",
      "road_width_m": 3.4,
      "section_index": 0,
      "start_node_id": "11398532935",
      "surface": null,
      "trim_end_m": 0,
      "trim_start_m": 0,
      "turn_lanes": null
    },
    {
      "centerline": [
        {
          "x": -309.982,
          "z": -30.702
        },
        {
          "x": -312.179,
          "z": -30.691
        },
        {
          "x": -322.766,
          "z": -30.602
        }
      ],
      "crossing": null,
      "end_node_id": "11398532938",
      "estimated_road_width_m": 3.4,
      "highway": "service",
      "id": "way/1229118431#section/0",
      "lane_count": 1,
      "lane_source": "inferred",
      "lane_width_m": 3.4,
      "maxspeed": null,
      "name": null,
      "oneway": false,
      "parent_id": "way/1229118431",
      "render_kind": "road",
      "road_width_m": 3.4,
      "section_index": 0,
      "start_node_id": "11398532934",
      "surface": null,
      "trim_end_m": 0,
      "trim_start_m": 0,
      "turn_lanes": null
    },
    {
      "centerline": [
        {
          "x": -309.973,
          "z": -13.002
        },
        {
          "x": -309.982,
          "z": -30.702
        }
      ],
      "crossing": null,
      "end_node_id": "11398532934",
      "estimated_road_width_m": 3.4,
      "highway": "service",
      "id": "way/1229118432#section/0",
      "lane_count": 1,
      "lane_source": "inferred",
      "lane_width_m": 3.4,
      "maxspeed": null,
      "name": null,
      "oneway": true,
      "parent_id": "way/1229118432",
      "render_kind": "road",
      "road_width_m": 3.4,
      "section_index": 0,
      "start_node_id": "11398532933",
      "surface": null,
      "trim_end_m": 0,
      "trim_start_m": 0,
      "turn_lanes": null
    },
    {
      "centerline": [
        {
          "x": -309.982,
          "z": -30.702
        },
        {
          "x": -294.42,
          "z": -30.68
        }
      ],
      "crossing": null,
      "end_node_id": "11398532935",
      "estimated_road_width_m": 3.4,
      "highway": "service",
      "id": "way/1229118433#section/0",
      "lane_count": 1,
      "lane_source": "inferred",
      "lane_width_m": 3.4,
      "maxspeed": null,
      "name": null,
      "oneway": false,
      "parent_id": "way/1229118433",
      "render_kind": "road",
      "road_width_m": 3.4,
      "section_index": 0,
      "start_node_id": "11398532934",
      "surface": null,
      "trim_end_m": 0,
      "trim_start_m": 0,
      "turn_lanes": null
    },
    {
      "centerline": [
        {
          "x": -293.313,
          "z": -13.971
        },
        {
          "x": -295.574,
          "z": -13.781
        },
        {
          "x": -307.508,
          "z": -14.049
        },
        {
          "x": -308.413,
          "z": -11.767
        }
      ],
      "crossing": null,
      "end_node_id": "11398532939",
      "estimated_road_width_m": 3.4,
      "highway": "service",
      "id": "way/1229118434#section/0",
      "lane_count": 1,
      "lane_source": "inferred",
      "lane_width_m": 3.4,
      "maxspeed": null,
      "name": null,
      "oneway": true,
      "parent_id": "way/1229118434",
      "render_kind": "road",
      "road_width_m": 3.4,
      "section_index": 0,
      "start_node_id": "11398532942",
      "surface": null,
      "trim_end_m": 0,
      "trim_start_m": 0,
      "turn_lanes": null
    },
    {
      "centerline": [
        {
          "x": -293.313,
          "z": -13.971
        },
        {
          "x": -295.842,
          "z": -11.31
        }
      ],
      "crossing": null,
      "end_node_id": "11398532943",
      "estimated_road_width_m": 3.4,
      "highway": "service",
      "id": "way/1229118435#section/0",
      "lane_count": 1,
      "lane_source": "inferred",
      "lane_width_m": 3.4,
      "maxspeed": null,
      "name": null,
      "oneway": true,
      "parent_id": "way/1229118435",
      "render_kind": "road",
      "road_width_m": 3.4,
      "section_index": 0,
      "start_node_id": "11398532942",
      "surface": null,
      "trim_end_m": 0,
      "trim_start_m": 0,
      "turn_lanes": null
    },
    {
      "centerline": [
        {
          "x": -120.508,
          "z": -90.503
        },
        {
          "x": -274.769,
          "z": -90.737
        }
      ],
      "crossing": null,
      "end_node_id": "6768739143",
      "estimated_road_width_m": 6.8,
      "highway": "residential",
      "id": "way/1266590558#section/2",
      "lane_count": 2,
      "lane_source": "inferred",
      "lane_width_m": 3.4,
      "maxspeed": null,
      "name": "West 58th Place",
      "oneway": false,
      "parent_id": "way/1266590558",
      "render_kind": "road",
      "road_width_m": 6.8,
      "section_index": 2,
      "start_node_id": "122601743",
      "surface": "paved",
      "trim_end_m": 0,
      "trim_start_m": 0,
      "turn_lanes": null
    },
    {
      "centerline": [
        {
          "x": -274.769,
          "z": -90.737
        },
        {
          "x": -322.941,
          "z": -91.461
        }
      ],
      "crossing": null,
      "end_node_id": "123224180",
      "estimated_road_width_m": 6.8,
      "highway": "residential",
      "id": "way/1266590558#section/3",
      "lane_count": 2,
      "lane_source": "inferred",
      "lane_width_m": 3.4,
      "maxspeed": null,
      "name": "West 58th Place",
      "oneway": false,
      "parent_id": "way/1266590558",
      "render_kind": "road",
      "road_width_m": 6.8,
      "section_index": 3,
      "start_node_id": "6768739143",
      "surface": "paved",
      "trim_end_m": 0,
      "trim_start_m": 0,
      "turn_lanes": null
    }
  ],
  "terrain": {
    "columns": 2,
    "origin_elevation_m": 58.0,
    "points": [
      {
        "elevation_m": 62.0,
        "relative_y_m": 4.0,
        "x": -360.0,
        "z": -180.0
      },
      {
        "elevation_m": 59.0,
        "relative_y_m": 1.0,
        "x": -180.0,
        "z": -180.0
      },
      {
        "elevation_m": 64.0,
        "relative_y_m": 6.0,
        "x": -360.0,
        "z": 0.0
      },
      {
        "elevation_m": 61.0,
        "relative_y_m": 3.0,
        "x": -180.0,
        "z": 0.0
      }
    ],
    "rows": 2,
    "schema": "gangland.unity_city_terrain.v1",
    "source": "Open-Meteo Elevation API, Copernicus DEM GLO-90",
    "spacing_m": 180
  }
}
